{
  "bin": {
    "cut": "tag_Ele_pt > 40 && abs(tag_sc_eta) < 2.17 && (tag_Ele_q + el_q) == 0 &&(((el_pt > 7) &&(abs(el_sc_eta) < 2.5) &&(abs(el_dz) < 1.0) &&(abs(el_dxy) < 0.5) &&(el_sc_et > 10) && (    (abs(el_sc_eta) < 0.8   && el_hzzMVA > 0.3527) || (abs(el_sc_eta) >= 0.8  && abs(el_sc_eta) < 1.479 && el_hzzMVA > 0.2601) || (abs(el_sc_eta) >= 1.479 && el_hzzMVA > -0.4954) )&& ( (passHltEle23Ele12CaloIdLTrackIdLIsoVLLeg2 == 1) || (passHltEle23Ele12CaloIdLTrackIdLIsoVLLeg1L1match == 1) || (passHltEle30WPTightGsf == 1))) || ((el_pt > 7) &&(abs(el_sc_eta) < 2.5) &&(abs(el_dz) < 1.0) &&(abs(el_dxy) < 0.5) &&(el_sc_et < 10) && (    (abs(el_sc_eta) < 0.8   && el_hzzMVA > 0.9267) || (abs(el_sc_eta) >= 0.8  && abs(el_sc_eta) < 1.479 && el_hzzMVA > 0.9138) || (abs(el_sc_eta) >= 1.479 && el_hzzMVA > 0.9683) )&& ( (passHltEle23Ele12CaloIdLTrackIdLIsoVLLeg2 == 1) || (passHltEle23Ele12CaloIdLTrackIdLIsoVLLeg1L1match == 1) || (passHltEle30WPTightGsf == 1)))) && el_sc_eta >= -2.000000 && el_sc_eta < -1.566000 && el_et >= 15.000000 && el_et < 20.000000",
    "index": 9,
    "name": "bin09_el_sc_eta_m2p00Tom1p57_el_et_15p00To20p00",
    "title": "; -2.000 < el_sc_eta < -1.566; 15.000 < el_et < 20.000",
    "vars": {
      "el_et": {
        "max": 20,
        "min": 15
      },
      "el_sc_eta": {
        "max": -1.566,
        "min": -2.0
      }
    }
  },
  "created_at_utc": "2026-05-06T14:33:24.335376+00:00",
  "derived": {
    "efficiency": 0.96042225951207,
    "efficiency_error": 0.0012611708965039946,
    "nSigF": {
      "error": 104.80361760841743,
      "isConstant": false,
      "max": 7698.0,
      "min": 0.5,
      "name": "nSigF",
      "value": 3187.906365738329
    },
    "nSigP": {
      "error": 346.33419294082705,
      "isConstant": false,
      "max": 129625.5,
      "min": 0.5,
      "name": "nSigP",
      "value": 77360.0563637294
    }
  },
  "fit_metadata": {
    "bin_index": 9,
    "fail_hist_uses_pass_hist": false,
    "fit_range": {
      "max": 120.0,
      "min": 60.0
    },
    "truth_fail_template_uses_pass_hist": false,
    "truth_template_source": "/eos/home-p/pelai/HZa/root_TnP//hza_elminiIso0p15_nongap_2024_sf//DY_MC_LO_2024_hza_elminiIso0p15_nongap_2024_sf.root"
  },
  "fit_result": {
    "fail": {
      "covQual": 3,
      "edm": 0.00030231090051874407,
      "floatParsFinal": [
        {
          "error": 1.4757087725754223,
          "isConstant": false,
          "max": 3.5,
          "min": 1.4,
          "name": "alphaF",
          "value": 1.4000063819754964
        },
        {
          "error": 0.0028835044775075147,
          "isConstant": false,
          "max": 0.05,
          "min": -1.0,
          "name": "alphaF_2",
          "value": -0.0481224509910515
        },
        {
          "error": 0.8864928089054753,
          "isConstant": false,
          "max": 5.0,
          "min": -5.0,
          "name": "meanF",
          "value": -0.17879074607270518
        },
        {
          "error": 94.29360942533913,
          "isConstant": false,
          "max": 7698.0,
          "min": 0.5,
          "name": "nBkgF",
          "value": 1096.0803011611088
        },
        {
          "error": 0.2183596344177556,
          "isConstant": false,
          "max": 1.5,
          "min": 0.0,
          "name": "nF",
          "value": 0.6894161816231584
        },
        {
          "error": 104.80361760841743,
          "isConstant": false,
          "max": 7698.0,
          "min": 0.5,
          "name": "nSigF",
          "value": 3187.906365738329
        },
        {
          "error": 1.4470040815127012,
          "isConstant": false,
          "max": 2.0,
          "min": 0.1,
          "name": "sigmaF",
          "value": 1.9999993361213129
        },
        {
          "error": 1.9701525434937208,
          "isConstant": false,
          "max": 3.0,
          "min": 0.1,
          "name": "sigmaF_2",
          "value": 0.10000622237252293
        },
        {
          "error": 0.7039080744592843,
          "isConstant": false,
          "max": 1.0,
          "min": 0.0,
          "name": "sosF",
          "value": 0.5912648235451917
        }
      ],
      "floatParsInit": [
        {
          "error": 0.0,
          "isConstant": false,
          "max": 3.5,
          "min": 1.4,
          "name": "alphaF",
          "value": 2.0
        },
        {
          "error": 0.0,
          "isConstant": false,
          "max": 0.05,
          "min": -1.0,
          "name": "alphaF_2",
          "value": -0.014
        },
        {
          "error": 0.0,
          "isConstant": false,
          "max": 5.0,
          "min": -5.0,
          "name": "meanF",
          "value": -0.0
        },
        {
          "error": 0.0,
          "isConstant": false,
          "max": 7698.0,
          "min": 0.5,
          "name": "nBkgF",
          "value": 513.2
        },
        {
          "error": 0.0,
          "isConstant": false,
          "max": 1.5,
          "min": 0.0,
          "name": "nF",
          "value": 0.4
        },
        {
          "error": 0.0,
          "isConstant": false,
          "max": 7698.0,
          "min": 0.5,
          "name": "nSigF",
          "value": 4618.8
        },
        {
          "error": 0.0,
          "isConstant": false,
          "max": 2.0,
          "min": 0.1,
          "name": "sigmaF",
          "value": 0.5
        },
        {
          "error": 0.0,
          "isConstant": false,
          "max": 3.0,
          "min": 0.1,
          "name": "sigmaF_2",
          "value": 0.5
        },
        {
          "error": 0.0,
          "isConstant": false,
          "max": 1.0,
          "min": 0.0,
          "name": "sosF",
          "value": 0.12
        }
      ],
      "minNll": -15526.27401090564,
      "numInvalidNLL": 0,
      "status": 0
    },
    "fail_quality": "ok",
    "pass": {
      "covQual": 2,
      "edm": 0.1943175040254124,
      "floatParsFinal": [
        {
          "error": 0.024083796586825246,
          "isConstant": false,
          "max": 3.5,
          "min": 1.4,
          "name": "alphaP",
          "value": 1.4033944374027378
        },
        {
          "error": 0.0024023699841250745,
          "isConstant": false,
          "max": 0.0,
          "min": -1.0,
          "name": "alphaP_2",
          "value": -0.04163176746044406
        },
        {
          "error": 0.03829252959640428,
          "isConstant": false,
          "max": 5.0,
          "min": -5.0,
          "name": "meanP",
          "value": -0.09512170881511395
        },
        {
          "error": 280.0726697265061,
          "isConstant": false,
          "max": 129625.5,
          "min": 0.5,
          "name": "nBkgP",
          "value": 3429.948618473958
        },
        {
          "error": 0.012834004644836819,
          "isConstant": false,
          "max": 1.5,
          "min": 0.0,
          "name": "nP",
          "value": 0.14763803842880777
        },
        {
          "error": 346.33419294082705,
          "isConstant": false,
          "max": 129625.5,
          "min": 0.5,
          "name": "nSigP",
          "value": 77360.0563637294
        },
        {
          "error": 0.028495584687820597,
          "isConstant": false,
          "max": 2.0,
          "min": 0.1,
          "name": "sigmaP",
          "value": 0.42497650970461975
        },
        {
          "error": 0.0013713894464252863,
          "isConstant": false,
          "max": 2.0,
          "min": 0.1,
          "name": "sigmaP_2",
          "value": 0.4594738322584295
        },
        {
          "error": 0.6309345542369856,
          "isConstant": false,
          "max": 1.0,
          "min": 0.0,
          "name": "sosP",
          "value": 0.07263328035347622
        }
      ],
      "floatParsInit": [
        {
          "error": 0.0,
          "isConstant": false,
          "max": 3.5,
          "min": 1.4,
          "name": "alphaP",
          "value": 2.0
        },
        {
          "error": 0.0,
          "isConstant": false,
          "max": 0.0,
          "min": -1.0,
          "name": "alphaP_2",
          "value": -0.012
        },
        {
          "error": 0.0,
          "isConstant": false,
          "max": 5.0,
          "min": -5.0,
          "name": "meanP",
          "value": -0.0
        },
        {
          "error": 0.0,
          "isConstant": false,
          "max": 129625.5,
          "min": 0.5,
          "name": "nBkgP",
          "value": 8641.7
        },
        {
          "error": 0.0,
          "isConstant": false,
          "max": 1.5,
          "min": 0.0,
          "name": "nP",
          "value": 0.4
        },
        {
          "error": 0.0,
          "isConstant": false,
          "max": 129625.5,
          "min": 0.5,
          "name": "nSigP",
          "value": 77775.3
        },
        {
          "error": 0.0,
          "isConstant": false,
          "max": 2.0,
          "min": 0.1,
          "name": "sigmaP",
          "value": 0.5
        },
        {
          "error": 0.0,
          "isConstant": false,
          "max": 2.0,
          "min": 0.1,
          "name": "sigmaP_2",
          "value": 0.5
        },
        {
          "error": 0.0,
          "isConstant": false,
          "max": 1.0,
          "min": 0.0,
          "name": "sosP",
          "value": 0.1
        }
      ],
      "minNll": -549066.9500696992,
      "numInvalidNLL": 0,
      "status": 3
    },
    "pass_quality": "check",
    "root_read_error": null
  },
  "fit_type": "altSigBkgFit",
  "histograms": {
    "fail": {
      "entries": 5132.0,
      "fit_window": {
        "bin1": 11,
        "bin2": 70,
        "max": 120.0,
        "min": 60.0
      },
      "integral_fit_window": 4284.0,
      "integral_fit_window_error": 65.45227268781429,
      "integral_full": 5132.0,
      "integral_full_error": 71.63797875428926,
      "maximum_bin_center": 89.5,
      "maximum_bin_content": 195.0,
      "mean": 77.30248131384073,
      "rms": 14.615460018582894
    },
    "pass": {
      "entries": 86417.0,
      "fit_window": {
        "bin1": 11,
        "bin2": 70,
        "max": 120.0,
        "min": 60.0
      },
      "integral_fit_window": 80684.0,
      "integral_fit_window_error": 284.0492914970921,
      "integral_full": 86417.0,
      "integral_full_error": 293.9676852989117,
      "maximum_bin_center": 89.5,
      "maximum_bin_content": 5164.0,
      "mean": 83.320139287618,
      "rms": 11.4856962713983
    }
  },
  "sample": {
    "fitOutputBinRoot": "/eos/home-p/pelai/HZa/root_TnP//hza_elminiIso0p15_nongap_2024_sf//Data_2024_hza_elminiIso0p15_nongap_2024_sf.altSigBkgFit-bin09_el_sc_eta_m2p00Tom1p57_el_et_15p00To20p00.root",
    "fitOutputRoot": "/eos/home-p/pelai/HZa/root_TnP//hza_elminiIso0p15_nongap_2024_sf//Data_2024_hza_elminiIso0p15_nongap_2024_sf.altSigBkgFit.root",
    "histFile": "/eos/home-p/pelai/HZa/root_TnP//hza_elminiIso0p15_nongap_2024_sf//Data_2024_hza_elminiIso0p15_nongap_2024_sf.root",
    "isMC": false,
    "mcRefHistFile": "/eos/home-p/pelai/HZa/root_TnP//hza_elminiIso0p15_nongap_2024_sf//DY_MC_LO_2024_hza_elminiIso0p15_nongap_2024_sf.root",
    "mcTruth": false,
    "name": "Data_2024"
  },
  "workspace": {
    "effective_parsed": [
      {
        "max": 5.0,
        "min": -5.0,
        "name": "meanP",
        "raw": "meanP[-0.0, -5.0, 5.0]",
        "tokens": [
          "-0.0",
          "-5.0",
          "5.0"
        ],
        "value": -0.0
      },
      {
        "max": 5.0,
        "min": -5.0,
        "name": "meanF",
        "raw": "meanF[-0.0, -5.0, 5.0]",
        "tokens": [
          "-0.0",
          "-5.0",
          "5.0"
        ],
        "value": -0.0
      },
      {
        "max": 2.0,
        "min": 0.1,
        "name": "sigmaP",
        "raw": "sigmaP[0.5, 0.1, 2.0]",
        "tokens": [
          "0.5",
          "0.1",
          "2.0"
        ],
        "value": 0.5
      },
      {
        "max": 2.0,
        "min": 0.1,
        "name": "sigmaF",
        "raw": "sigmaF[0.5, 0.1, 2.0]",
        "tokens": [
          "0.5",
          "0.1",
          "2.0"
        ],
        "value": 0.5
      },
      {
        "max": 2.0,
        "min": 0.1,
        "name": "sigmaP_2",
        "raw": "sigmaP_2[0.5, 0.1, 2.0]",
        "tokens": [
          "0.5",
          "0.1",
          "2.0"
        ],
        "value": 0.5
      },
      {
        "max": 3.0,
        "min": 0.1,
        "name": "sigmaF_2",
        "raw": "sigmaF_2[0.5, 0.1, 3.0]",
        "tokens": [
          "0.5",
          "0.1",
          "3.0"
        ],
        "value": 0.5
      },
      {
        "max": 1.0,
        "min": 0.0,
        "name": "sosP",
        "raw": "sosP[0.10, 0.0, 1.0]",
        "tokens": [
          "0.10",
          "0.0",
          "1.0"
        ],
        "value": 0.1
      },
      {
        "max": 1.0,
        "min": 0.0,
        "name": "sosF",
        "raw": "sosF[0.12, 0.0, 1.0]",
        "tokens": [
          "0.12",
          "0.0",
          "1.0"
        ],
        "value": 0.12
      },
      {
        "max": 3.5,
        "min": 1.4,
        "name": "alphaP",
        "raw": "alphaP[2.0, 1.4, 3.5]",
        "tokens": [
          "2.0",
          "1.4",
          "3.5"
        ],
        "value": 2.0
      },
      {
        "max": 1.5,
        "min": 0.0,
        "name": "nP",
        "raw": "nP[0.4, 0.0, 1.5]",
        "tokens": [
          "0.4",
          "0.0",
          "1.5"
        ],
        "value": 0.4
      },
      {
        "max": 3.5,
        "min": 1.4,
        "name": "alphaF",
        "raw": "alphaF[2.0, 1.4, 3.5]",
        "tokens": [
          "2.0",
          "1.4",
          "3.5"
        ],
        "value": 2.0
      },
      {
        "max": 1.5,
        "min": 0.0,
        "name": "nF",
        "raw": "nF[0.4, 0.0, 1.5]",
        "tokens": [
          "0.4",
          "0.0",
          "1.5"
        ],
        "value": 0.4
      },
      {
        "max": 0.0,
        "min": -1.0,
        "name": "alphaP_2",
        "raw": "alphaP_2[-0.012, -1, 0]",
        "tokens": [
          "-0.012",
          "-1",
          "0"
        ],
        "value": -0.012
      },
      {
        "max": 0.05,
        "min": -1.0,
        "name": "alphaF_2",
        "raw": "alphaF_2[-0.014, -1, 0.05]",
        "tokens": [
          "-0.014",
          "-1",
          "0.05"
        ],
        "value": -0.014
      }
    ],
    "effective_raw": [
      "meanP[-0.0, -5.0, 5.0]",
      "meanF[-0.0, -5.0, 5.0]",
      "sigmaP[0.5, 0.1, 2.0]",
      "sigmaF[0.5, 0.1, 2.0]",
      "sigmaP_2[0.5, 0.1, 2.0]",
      "sigmaF_2[0.5, 0.1, 3.0]",
      "sosP[0.10, 0.0, 1.0]",
      "sosF[0.12, 0.0, 1.0]",
      "alphaP[2.0, 1.4, 3.5]",
      "nP[0.4, 0.0, 1.5]",
      "alphaF[2.0, 1.4, 3.5]",
      "nF[0.4, 0.0, 1.5]",
      "alphaP_2[-0.012, -1, 0]",
      "alphaF_2[-0.014, -1, 0.05]"
    ],
    "functions": [
      "tailLeft[1]",
      "RooCBExGaussShapeTNP::sigResPass(x,meanP,expr('sqrt(sigmaP*sigmaP+sosP*sosP)',{sigmaP,sosP}),alphaP,nP, expr('sqrt(sigmaP_2*sigmaP_2+sosP*sosP)',{sigmaP_2,sosP}),tailLeft)",
      "RooCBExGaussShapeTNP::sigResFail(x,meanF,expr('sqrt(sigmaF*sigmaF+sosF*sosF)',{sigmaF,sosF}),alphaF,nF, expr('sqrt(sigmaF_2*sigmaF_2+sosF*sosF)',{sigmaF_2,sosF}),tailLeft)",
      "Exponential::bkgPass(x, alphaP_2)",
      "Exponential::bkgFail(x, alphaF_2)"
    ],
    "overrides": [],
    "requested_parsed": [
      {
        "max": 5.0,
        "min": -5.0,
        "name": "meanP",
        "raw": "meanP[-0.0, -5.0, 5.0]",
        "tokens": [
          "-0.0",
          "-5.0",
          "5.0"
        ],
        "value": -0.0
      },
      {
        "max": 5.0,
        "min": -5.0,
        "name": "meanF",
        "raw": "meanF[-0.0, -5.0, 5.0]",
        "tokens": [
          "-0.0",
          "-5.0",
          "5.0"
        ],
        "value": -0.0
      },
      {
        "max": 2.0,
        "min": 0.1,
        "name": "sigmaP",
        "raw": "sigmaP[0.5, 0.1, 2.0]",
        "tokens": [
          "0.5",
          "0.1",
          "2.0"
        ],
        "value": 0.5
      },
      {
        "max": 2.0,
        "min": 0.1,
        "name": "sigmaF",
        "raw": "sigmaF[0.5, 0.1, 2.0]",
        "tokens": [
          "0.5",
          "0.1",
          "2.0"
        ],
        "value": 0.5
      },
      {
        "max": 2.0,
        "min": 0.1,
        "name": "sigmaP_2",
        "raw": "sigmaP_2[0.5, 0.1, 2.0]",
        "tokens": [
          "0.5",
          "0.1",
          "2.0"
        ],
        "value": 0.5
      },
      {
        "max": 3.0,
        "min": 0.1,
        "name": "sigmaF_2",
        "raw": "sigmaF_2[0.5, 0.1, 3.0]",
        "tokens": [
          "0.5",
          "0.1",
          "3.0"
        ],
        "value": 0.5
      },
      {
        "max": 1.0,
        "min": 0.0,
        "name": "sosP",
        "raw": "sosP[0.10, 0.0, 1.0]",
        "tokens": [
          "0.10",
          "0.0",
          "1.0"
        ],
        "value": 0.1
      },
      {
        "max": 1.0,
        "min": 0.0,
        "name": "sosF",
        "raw": "sosF[0.12, 0.0, 1.0]",
        "tokens": [
          "0.12",
          "0.0",
          "1.0"
        ],
        "value": 0.12
      },
      {
        "max": 3.5,
        "min": 1.4,
        "name": "alphaP",
        "raw": "alphaP[2.0, 1.4, 3.5]",
        "tokens": [
          "2.0",
          "1.4",
          "3.5"
        ],
        "value": 2.0
      },
      {
        "max": 1.5,
        "min": 0.0,
        "name": "nP",
        "raw": "nP[0.4, 0.0, 1.5]",
        "tokens": [
          "0.4",
          "0.0",
          "1.5"
        ],
        "value": 0.4
      },
      {
        "max": 3.5,
        "min": 1.4,
        "name": "alphaF",
        "raw": "alphaF[2.0, 1.4, 3.5]",
        "tokens": [
          "2.0",
          "1.4",
          "3.5"
        ],
        "value": 2.0
      },
      {
        "max": 1.5,
        "min": 0.0,
        "name": "nF",
        "raw": "nF[0.4, 0.0, 1.5]",
        "tokens": [
          "0.4",
          "0.0",
          "1.5"
        ],
        "value": 0.4
      },
      {
        "max": 0.0,
        "min": -1.0,
        "name": "alphaP_2",
        "raw": "alphaP_2[-0.012, -1, 0]",
        "tokens": [
          "-0.012",
          "-1",
          "0"
        ],
        "value": -0.012
      },
      {
        "max": 0.05,
        "min": -1.0,
        "name": "alphaF_2",
        "raw": "alphaF_2[-0.014, -1, 0.05]",
        "tokens": [
          "-0.014",
          "-1",
          "0.05"
        ],
        "value": -0.014
      }
    ],
    "requested_raw": [
      "meanP[-0.0, -5.0, 5.0]",
      "meanF[-0.0, -5.0, 5.0]",
      "sigmaP[0.5, 0.1, 2.0]",
      "sigmaF[0.5, 0.1, 2.0]",
      "sigmaP_2[0.5, 0.1, 2.0]",
      "sigmaF_2[0.5, 0.1, 3.0]",
      "sosP[0.10, 0.0, 1.0]",
      "sosF[0.12, 0.0, 1.0]",
      "alphaP[2.0, 1.4, 3.5]",
      "nP[0.4, 0.0, 1.5]",
      "alphaF[2.0, 1.4, 3.5]",
      "nF[0.4, 0.0, 1.5]",
      "alphaP_2[-0.012, -1, 0]",
      "alphaF_2[-0.014, -1, 0.05]"
    ]
  }
}
