{
  "bin": {
    "cut": "ph_r9 > 0.96 && event_nPV >= 40.000000 && event_nPV < 50.000000 && ph_et >= 50.000000 && ph_et < 80.000000",
    "index": 30,
    "name": "bin30_event_nPV_40p00To50p00_ph_et_50p00To80p00",
    "title": "; 40.000 < event_nPV < 50.000; 50.000 < ph_et < 80.000",
    "vars": {
      "event_nPV": {
        "max": 50,
        "min": 40
      },
      "ph_et": {
        "max": 80,
        "min": 50
      }
    }
  },
  "created_at_utc": "2026-05-10T17:33:04.230318+00:00",
  "derived": {
    "efficiency": 0.8904254348175749,
    "efficiency_error": 0.010388854474226428,
    "nSigF": {
      "error": 0.0,
      "isConstant": false,
      "max": 18.0,
      "min": 0.5,
      "name": "nSigF",
      "value": 10.8
    },
    "nSigP": {
      "error": 9.344840784610632,
      "isConstant": false,
      "max": 132.0,
      "min": 0.5,
      "name": "nSigP",
      "value": 87.76301945638224
    }
  },
  "fit_metadata": {
    "bin_index": 30,
    "fail_hist_uses_pass_hist": false,
    "fit_range": {
      "max": 120.0,
      "min": 60.0
    },
    "truth_fail_template_uses_pass_hist": false,
    "truth_template_source": "/eos/home-p/pelai/HZa/root_TnP/hza_resolve_phcsev_hr9_2022postEE_sf//DY_MC_NLO_2022postEE_hza_resolve_phcsev_hr9_2022postEE_sf.root"
  },
  "fit_result": {
    "fail": {
      "covQual": 0,
      "edm": 3.2357843125153494,
      "floatParsFinal": [
        {
          "error": 0.0,
          "isConstant": false,
          "max": 5.0,
          "min": -5.0,
          "name": "alphaF",
          "value": 0.0
        },
        {
          "error": 0.0,
          "isConstant": false,
          "max": 5.0,
          "min": -5.0,
          "name": "meanF",
          "value": 0.0
        },
        {
          "error": 0.0,
          "isConstant": false,
          "max": 18.0,
          "min": 0.5,
          "name": "nBkgF",
          "value": 1.1999999999999997
        },
        {
          "error": 0.0,
          "isConstant": false,
          "max": 18.0,
          "min": 0.5,
          "name": "nSigF",
          "value": 10.8
        },
        {
          "error": 0.0,
          "isConstant": false,
          "max": 5.0,
          "min": 0.5,
          "name": "sigmaF",
          "value": 0.9000000000000001
        }
      ],
      "floatParsInit": [
        {
          "error": 0.0,
          "isConstant": false,
          "max": 5.0,
          "min": -5.0,
          "name": "alphaF",
          "value": 0.0
        },
        {
          "error": 0.0,
          "isConstant": false,
          "max": 5.0,
          "min": -5.0,
          "name": "meanF",
          "value": -0.0
        },
        {
          "error": 0.0,
          "isConstant": false,
          "max": 18.0,
          "min": 0.5,
          "name": "nBkgF",
          "value": 1.2
        },
        {
          "error": 0.0,
          "isConstant": false,
          "max": 18.0,
          "min": 0.5,
          "name": "nSigF",
          "value": 10.8
        },
        {
          "error": 0.0,
          "isConstant": false,
          "max": 5.0,
          "min": 0.5,
          "name": "sigmaF",
          "value": 0.9
        }
      ],
      "minNll": -1e+30,
      "numInvalidNLL": 0,
      "status": 303
    },
    "fail_quality": "check",
    "pass": {
      "covQual": 3,
      "edm": 0.00044334621758269265,
      "floatParsFinal": [
        {
          "error": 0.1297075722929928,
          "isConstant": false,
          "max": 5.0,
          "min": -5.0,
          "name": "alphaP",
          "value": -0.004259647233887165
        },
        {
          "error": 0.4169949619217994,
          "isConstant": false,
          "max": 5.0,
          "min": -5.0,
          "name": "meanP",
          "value": 0.009769074085030027
        },
        {
          "error": 0.9360225192050552,
          "isConstant": false,
          "max": 132.0,
          "min": 0.5,
          "name": "nBkgP",
          "value": 0.5000063204886762
        },
        {
          "error": 9.344840784610632,
          "isConstant": false,
          "max": 132.0,
          "min": 0.5,
          "name": "nSigP",
          "value": 87.76301945638224
        },
        {
          "error": 0.3598545684408636,
          "isConstant": false,
          "max": 5.0,
          "min": 0.5,
          "name": "sigmaP",
          "value": 3.1848865106412267
        }
      ],
      "floatParsInit": [
        {
          "error": 0.0,
          "isConstant": false,
          "max": 5.0,
          "min": -5.0,
          "name": "alphaP",
          "value": 0.0
        },
        {
          "error": 0.0,
          "isConstant": false,
          "max": 5.0,
          "min": -5.0,
          "name": "meanP",
          "value": -0.0
        },
        {
          "error": 0.0,
          "isConstant": false,
          "max": 132.0,
          "min": 0.5,
          "name": "nBkgP",
          "value": 8.8
        },
        {
          "error": 0.0,
          "isConstant": false,
          "max": 132.0,
          "min": 0.5,
          "name": "nSigP",
          "value": 79.2
        },
        {
          "error": 0.0,
          "isConstant": false,
          "max": 5.0,
          "min": 0.5,
          "name": "sigmaP",
          "value": 0.9
        }
      ],
      "minNll": -61.31645590796734,
      "numInvalidNLL": 0,
      "status": 0
    },
    "pass_quality": "ok",
    "root_read_error": null
  },
  "fit_type": "altBkgFit",
  "histograms": {
    "fail": {
      "entries": 12.0,
      "fit_window": {
        "bin1": 11,
        "bin2": 70,
        "max": 120.0,
        "min": 60.0
      },
      "integral_fit_window": 12.0,
      "integral_fit_window_error": 3.4641016151377544,
      "integral_full": 12.0,
      "integral_full_error": 3.4641016151377544,
      "maximum_bin_center": 94.5,
      "maximum_bin_content": 2.0,
      "mean": 89.9707711537679,
      "rms": 5.383090255110803
    },
    "pass": {
      "entries": 88.0,
      "fit_window": {
        "bin1": 11,
        "bin2": 70,
        "max": 120.0,
        "min": 60.0
      },
      "integral_fit_window": 88.0,
      "integral_fit_window_error": 9.38083151964686,
      "integral_full": 88.0,
      "integral_full_error": 9.38083151964686,
      "maximum_bin_center": 91.5,
      "maximum_bin_content": 18.0,
      "mean": 91.28293479572643,
      "rms": 3.8555752437832704
    }
  },
  "sample": {
    "fitOutputBinRoot": "/eos/home-p/pelai/HZa/root_TnP/hza_resolve_phcsev_hr9_2022postEE_sf//Data_2022postEE_hza_resolve_phcsev_hr9_2022postEE_sf.altBkgFit-bin30_event_nPV_40p00To50p00_ph_et_50p00To80p00.root",
    "fitOutputRoot": "/eos/home-p/pelai/HZa/root_TnP/hza_resolve_phcsev_hr9_2022postEE_sf//Data_2022postEE_hza_resolve_phcsev_hr9_2022postEE_sf.altBkgFit.root",
    "histFile": "/eos/home-p/pelai/HZa/root_TnP/hza_resolve_phcsev_hr9_2022postEE_sf//Data_2022postEE_hza_resolve_phcsev_hr9_2022postEE_sf.root",
    "isMC": false,
    "mcRefHistFile": "/eos/home-p/pelai/HZa/root_TnP/hza_resolve_phcsev_hr9_2022postEE_sf//DY_MC_NLO_2022postEE_hza_resolve_phcsev_hr9_2022postEE_sf.root",
    "mcTruth": false,
    "name": "Data_2022postEE"
  },
  "workspace": {
    "effective_parsed": [
      {
        "max": 5.0,
        "min": -5.0,
        "name": "meanP",
        "raw": "meanP[-0.0,-5.0,5.0]",
        "tokens": [
          "-0.0",
          "-5.0",
          "5.0"
        ],
        "value": -0.0
      },
      {
        "max": 5.0,
        "min": 0.5,
        "name": "sigmaP",
        "raw": "sigmaP[0.9,0.5,5.0]",
        "tokens": [
          "0.9",
          "0.5",
          "5.0"
        ],
        "value": 0.9
      },
      {
        "max": 5.0,
        "min": -5.0,
        "name": "meanF",
        "raw": "meanF[-0.0,-5.0,5.0]",
        "tokens": [
          "-0.0",
          "-5.0",
          "5.0"
        ],
        "value": -0.0
      },
      {
        "max": 5.0,
        "min": 0.5,
        "name": "sigmaF",
        "raw": "sigmaF[0.9,0.5,5.0]",
        "tokens": [
          "0.9",
          "0.5",
          "5.0"
        ],
        "value": 0.9
      },
      {
        "max": 5.0,
        "min": -5.0,
        "name": "alphaP",
        "raw": "alphaP[0.,-5.,5.]",
        "tokens": [
          "0.",
          "-5.",
          "5."
        ],
        "value": 0.0
      },
      {
        "max": 5.0,
        "min": -5.0,
        "name": "alphaF",
        "raw": "alphaF[0.,-5.,5.]",
        "tokens": [
          "0.",
          "-5.",
          "5."
        ],
        "value": 0.0
      }
    ],
    "effective_raw": [
      "meanP[-0.0,-5.0,5.0]",
      "sigmaP[0.9,0.5,5.0]",
      "meanF[-0.0,-5.0,5.0]",
      "sigmaF[0.9,0.5,5.0]",
      "alphaP[0.,-5.,5.]",
      "alphaF[0.,-5.,5.]"
    ],
    "functions": [
      "Gaussian::sigResPass(x,meanP,sigmaP)",
      "Gaussian::sigResFail(x,meanF,sigmaF)",
      "Exponential::bkgPass(x, alphaP)",
      "Exponential::bkgFail(x, alphaF)"
    ],
    "overrides": [],
    "requested_parsed": [
      {
        "max": 5.0,
        "min": -5.0,
        "name": "meanP",
        "raw": "meanP[-0.0,-5.0,5.0]",
        "tokens": [
          "-0.0",
          "-5.0",
          "5.0"
        ],
        "value": -0.0
      },
      {
        "max": 5.0,
        "min": 0.5,
        "name": "sigmaP",
        "raw": "sigmaP[0.9,0.5,5.0]",
        "tokens": [
          "0.9",
          "0.5",
          "5.0"
        ],
        "value": 0.9
      },
      {
        "max": 5.0,
        "min": -5.0,
        "name": "meanF",
        "raw": "meanF[-0.0,-5.0,5.0]",
        "tokens": [
          "-0.0",
          "-5.0",
          "5.0"
        ],
        "value": -0.0
      },
      {
        "max": 5.0,
        "min": 0.5,
        "name": "sigmaF",
        "raw": "sigmaF[0.9,0.5,5.0]",
        "tokens": [
          "0.9",
          "0.5",
          "5.0"
        ],
        "value": 0.9
      },
      {
        "max": 5.0,
        "min": -5.0,
        "name": "alphaP",
        "raw": "alphaP[0.,-5.,5.]",
        "tokens": [
          "0.",
          "-5.",
          "5."
        ],
        "value": 0.0
      },
      {
        "max": 5.0,
        "min": -5.0,
        "name": "alphaF",
        "raw": "alphaF[0.,-5.,5.]",
        "tokens": [
          "0.",
          "-5.",
          "5."
        ],
        "value": 0.0
      }
    ],
    "requested_raw": [
      "meanP[-0.0,-5.0,5.0]",
      "sigmaP[0.9,0.5,5.0]",
      "meanF[-0.0,-5.0,5.0]",
      "sigmaF[0.9,0.5,5.0]",
      "alphaP[0.,-5.,5.]",
      "alphaF[0.,-5.,5.]"
    ]
  }
}
