{
  "bin": {
    "cut": "tag_Ele_pt > 40 && abs(tag_sc_eta) < 2.17 && (tag_Ele_q + el_q) == 0 && el_hltE23E12leg1_dR < 0.3 && el_hltE23E12leg2_dR < 0.3 &&(((el_pt > 7) &&(abs(el_sc_eta) < 2.5) &&(abs(el_dz) < 1.0) &&(abs(el_dxy) < 0.5) &&(el_sc_et > 10) && (    (abs(el_sc_eta) < 0.8   && el_hzzMVA > 0.3527) || (abs(el_sc_eta) >= 0.8  && abs(el_sc_eta) < 1.479 && el_hzzMVA > 0.2601) || (abs(el_sc_eta) >= 1.479 && el_hzzMVA > -0.4954) )&& el_hltE23E12leg2_dR < 0.3&& ( (passHltEle23Ele12CaloIdLTrackIdLIsoVLLeg2 == 1) || (passHltEle23Ele12CaloIdLTrackIdLIsoVLLeg1L1match == 1) || (passHltEle30WPTightGsf == 1))) || ((el_pt > 7) &&(abs(el_sc_eta) < 2.5) &&(abs(el_dz) < 1.0) &&(abs(el_dxy) < 0.5) &&(el_sc_et < 10) && (    (abs(el_sc_eta) < 0.8   && el_hzzMVA > 0.9267) || (abs(el_sc_eta) >= 0.8  && abs(el_sc_eta) < 1.479 && el_hzzMVA > 0.9138) || (abs(el_sc_eta) >= 1.479 && el_hzzMVA > 0.9683) )&& el_hltE23E12leg2_dR < 0.3&& ( (passHltEle23Ele12CaloIdLTrackIdLIsoVLLeg2 == 1) || (passHltEle23Ele12CaloIdLTrackIdLIsoVLLeg1L1match == 1) || (passHltEle30WPTightGsf == 1)))) && el_sc_eta >= 0.800000 && el_sc_eta < 1.566000 && el_et >= 20.000000 && el_et < 35.000000",
    "index": 21,
    "name": "bin21_el_sc_eta_0p80To1p57_el_et_20p00To35p00",
    "title": "; 0.800 < el_sc_eta < 1.566; 20.000 < el_et < 35.000",
    "vars": {
      "el_et": {
        "max": 35,
        "min": 20
      },
      "el_sc_eta": {
        "max": 1.566,
        "min": 0.8
      }
    }
  },
  "created_at_utc": "2026-05-01T19:31:26.338135+00:00",
  "derived": {
    "efficiency": 0.9505754803544599,
    "efficiency_error": 0.00029232626155984413,
    "nSigF": {
      "error": 206.30213338300746,
      "isConstant": false,
      "max": 51492.0,
      "min": 0.5,
      "name": "nSigF",
      "value": 33805.915593476464
    },
    "nSigP": {
      "error": 789.321763305983,
      "isConstant": false,
      "max": 984117.0,
      "min": 0.5,
      "name": "nSigP",
      "value": 650184.8613715561
    }
  },
  "fit_metadata": {
    "bin_index": 21,
    "fail_hist_uses_pass_hist": false,
    "fit_range": {
      "max": 120.0,
      "min": 60.0
    },
    "truth_fail_template_uses_pass_hist": false,
    "truth_template_source": "/eos/home-p/pelai/HZa/root_TnP//hza_elminiIso0p1_nongap_2025_sf//DY_MC_LO_2025_hza_elminiIso0p1_nongap_2025_sf.root"
  },
  "fit_result": {
    "fail": {
      "covQual": 2,
      "edm": 0.006114719537914754,
      "floatParsFinal": [
        {
          "error": 0.4254543001503548,
          "isConstant": false,
          "max": 3.5,
          "min": 1.4,
          "name": "alphaF",
          "value": 1.4031205237218844
        },
        {
          "error": 0.015547082618693087,
          "isConstant": false,
          "max": 0.05,
          "min": -1.0,
          "name": "alphaF_2",
          "value": 0.007683293847732475
        },
        {
          "error": 0.1238083843682305,
          "isConstant": false,
          "max": 5.0,
          "min": -5.0,
          "name": "meanF",
          "value": -0.16262707953473843
        },
        {
          "error": 121.7651468813611,
          "isConstant": false,
          "max": 51492.0,
          "min": 0.5,
          "name": "nBkgF",
          "value": 293.5407943965187
        },
        {
          "error": 0.3700554998318385,
          "isConstant": false,
          "max": 1.5,
          "min": 0.0,
          "name": "nF",
          "value": 0.8742583815394798
        },
        {
          "error": 206.30213338300746,
          "isConstant": false,
          "max": 51492.0,
          "min": 0.5,
          "name": "nSigF",
          "value": 33805.915593476464
        },
        {
          "error": 3.008330002467024,
          "isConstant": false,
          "max": 5.174596012856631,
          "min": 1.3798922700951015,
          "name": "sigmaF",
          "value": 1.3798926394644495
        },
        {
          "error": 0.3278788415197374,
          "isConstant": false,
          "max": 3.0,
          "min": 0.1,
          "name": "sigmaF_2",
          "value": 1.2829898258215502
        },
        {
          "error": 0.9298958388223268,
          "isConstant": false,
          "max": 1.0,
          "min": 0.0,
          "name": "sosF",
          "value": 0.03924074271697836
        }
      ],
      "floatParsInit": [
        {
          "error": 0.0,
          "isConstant": false,
          "max": 3.5,
          "min": 1.4,
          "name": "alphaF",
          "value": 2.0
        },
        {
          "error": 0.0,
          "isConstant": false,
          "max": 0.05,
          "min": -1.0,
          "name": "alphaF_2",
          "value": -0.014
        },
        {
          "error": 0.0,
          "isConstant": false,
          "max": 5.0,
          "min": -5.0,
          "name": "meanF",
          "value": -0.0
        },
        {
          "error": 0.0,
          "isConstant": false,
          "max": 51492.0,
          "min": 0.5,
          "name": "nBkgF",
          "value": 3432.8
        },
        {
          "error": 0.0,
          "isConstant": false,
          "max": 1.5,
          "min": 0.0,
          "name": "nF",
          "value": 0.4
        },
        {
          "error": 0.0,
          "isConstant": false,
          "max": 51492.0,
          "min": 0.5,
          "name": "nSigF",
          "value": 30895.2
        },
        {
          "error": 0.0,
          "isConstant": false,
          "max": 5.174596012856631,
          "min": 1.3798922700951015,
          "name": "sigmaF",
          "value": 1.7248653376188767
        },
        {
          "error": 0.0,
          "isConstant": false,
          "max": 3.0,
          "min": 0.1,
          "name": "sigmaF_2",
          "value": 0.5
        },
        {
          "error": 0.0,
          "isConstant": false,
          "max": 1.0,
          "min": 0.0,
          "name": "sosF",
          "value": 0.12
        }
      ],
      "minNll": -204865.8723164879,
      "numInvalidNLL": 0,
      "status": 3
    },
    "fail_quality": "check",
    "pass": {
      "covQual": 2,
      "edm": 0.0810589562721034,
      "floatParsFinal": [
        {
          "error": 1.4055338420453842,
          "isConstant": false,
          "max": 3.5,
          "min": 1.4,
          "name": "alphaP",
          "value": 1.4002243051437893
        },
        {
          "error": 0.00021506741203297652,
          "isConstant": false,
          "max": 0.0,
          "min": -1.0,
          "name": "alphaP_2",
          "value": -1.4809421466921435e-08
        },
        {
          "error": 0.02293538857355415,
          "isConstant": false,
          "max": 5.0,
          "min": -5.0,
          "name": "meanP",
          "value": 0.14152046437953647
        },
        {
          "error": 227.78280295718287,
          "isConstant": false,
          "max": 984117.0,
          "min": 0.5,
          "name": "nBkgP",
          "value": 2272.7545334044194
        },
        {
          "error": 0.03048288629226359,
          "isConstant": false,
          "max": 1.5,
          "min": 0.0,
          "name": "nP",
          "value": 1.3837887892596186
        },
        {
          "error": 789.321763305983,
          "isConstant": false,
          "max": 984117.0,
          "min": 0.5,
          "name": "nSigP",
          "value": 650184.8613715561
        },
        {
          "error": 0.0798465064583106,
          "isConstant": false,
          "max": 2.0,
          "min": 0.1,
          "name": "sigmaP",
          "value": 1.7248653376188767
        },
        {
          "error": 0.032822414818636625,
          "isConstant": false,
          "max": 2.0,
          "min": 0.1,
          "name": "sigmaP_2",
          "value": 0.4700500802914379
        },
        {
          "error": 0.059308848831476746,
          "isConstant": false,
          "max": 1.0,
          "min": 0.0,
          "name": "sosP",
          "value": 0.9994977094508172
        }
      ],
      "floatParsInit": [
        {
          "error": 0.0,
          "isConstant": false,
          "max": 3.5,
          "min": 1.4,
          "name": "alphaP",
          "value": 2.0
        },
        {
          "error": 0.0,
          "isConstant": false,
          "max": 0.0,
          "min": -1.0,
          "name": "alphaP_2",
          "value": -0.012
        },
        {
          "error": 0.0,
          "isConstant": false,
          "max": 5.0,
          "min": -5.0,
          "name": "meanP",
          "value": -0.0
        },
        {
          "error": 0.0,
          "isConstant": false,
          "max": 984117.0,
          "min": 0.5,
          "name": "nBkgP",
          "value": 65607.8
        },
        {
          "error": 0.0,
          "isConstant": false,
          "max": 1.5,
          "min": 0.0,
          "name": "nP",
          "value": 0.4
        },
        {
          "error": 0.0,
          "isConstant": false,
          "max": 984117.0,
          "min": 0.5,
          "name": "nSigP",
          "value": 590470.2
        },
        {
          "error": 0.0,
          "isConstant": false,
          "max": 2.0,
          "min": 0.1,
          "name": "sigmaP",
          "value": 0.5
        },
        {
          "error": 0.0,
          "isConstant": false,
          "max": 2.0,
          "min": 0.1,
          "name": "sigmaP_2",
          "value": 0.5
        },
        {
          "error": 0.0,
          "isConstant": false,
          "max": 1.0,
          "min": 0.0,
          "name": "sosP",
          "value": 0.1
        }
      ],
      "minNll": -6007363.97331155,
      "numInvalidNLL": 0,
      "status": 3
    },
    "pass_quality": "check",
    "root_read_error": null
  },
  "fit_type": "altSigBkgFit",
  "histograms": {
    "fail": {
      "entries": 34328.0,
      "fit_window": {
        "bin1": 11,
        "bin2": 70,
        "max": 120.0,
        "min": 60.0
      },
      "integral_fit_window": 34101.0,
      "integral_fit_window_error": 184.66456075814872,
      "integral_full": 34328.0,
      "integral_full_error": 185.27816924829543,
      "maximum_bin_center": 89.5,
      "maximum_bin_content": 2140.0,
      "mean": 84.71811027022348,
      "rms": 8.229588046078847
    },
    "pass": {
      "entries": 656078.0,
      "fit_window": {
        "bin1": 11,
        "bin2": 70,
        "max": 120.0,
        "min": 60.0
      },
      "integral_fit_window": 652438.0,
      "integral_fit_window_error": 807.7363431219372,
      "integral_full": 656078.0,
      "integral_full_error": 809.9864196392431,
      "maximum_bin_center": 89.5,
      "maximum_bin_content": 59567.0,
      "mean": 87.58497368571429,
      "rms": 6.891118580878329
    }
  },
  "sample": {
    "fitOutputBinRoot": "/eos/home-p/pelai/HZa/root_TnP//hza_elminiIso0p1_nongap_2025_sf//Data_2025_hza_elminiIso0p1_nongap_2025_sf.altSigBkgFit-bin21_el_sc_eta_0p80To1p57_el_et_20p00To35p00.root",
    "fitOutputRoot": "/eos/home-p/pelai/HZa/root_TnP//hza_elminiIso0p1_nongap_2025_sf//Data_2025_hza_elminiIso0p1_nongap_2025_sf.altSigBkgFit.root",
    "histFile": "/eos/home-p/pelai/HZa/root_TnP//hza_elminiIso0p1_nongap_2025_sf//Data_2025_hza_elminiIso0p1_nongap_2025_sf.root",
    "isMC": false,
    "mcRefHistFile": "/eos/home-p/pelai/HZa/root_TnP//hza_elminiIso0p1_nongap_2025_sf//DY_MC_LO_2025_hza_elminiIso0p1_nongap_2025_sf.root",
    "mcTruth": false,
    "name": "Data_2025"
  },
  "workspace": {
    "effective_parsed": [
      {
        "max": 5.0,
        "min": -5.0,
        "name": "meanP",
        "raw": "meanP[-0.0, -5.0, 5.0]",
        "tokens": [
          "-0.0",
          "-5.0",
          "5.0"
        ],
        "value": -0.0
      },
      {
        "max": 5.0,
        "min": -5.0,
        "name": "meanF",
        "raw": "meanF[-0.0, -5.0, 5.0]",
        "tokens": [
          "-0.0",
          "-5.0",
          "5.0"
        ],
        "value": -0.0
      },
      {
        "max": 2.0,
        "min": 0.1,
        "name": "sigmaP",
        "raw": "sigmaP[0.5, 0.1, 2.0]",
        "tokens": [
          "0.5",
          "0.1",
          "2.0"
        ],
        "value": 0.5
      },
      {
        "max": 2.0,
        "min": 0.1,
        "name": "sigmaF",
        "raw": "sigmaF[0.5, 0.1, 2.0]",
        "tokens": [
          "0.5",
          "0.1",
          "2.0"
        ],
        "value": 0.5
      },
      {
        "max": 2.0,
        "min": 0.1,
        "name": "sigmaP_2",
        "raw": "sigmaP_2[0.5, 0.1, 2.0]",
        "tokens": [
          "0.5",
          "0.1",
          "2.0"
        ],
        "value": 0.5
      },
      {
        "max": 3.0,
        "min": 0.1,
        "name": "sigmaF_2",
        "raw": "sigmaF_2[0.5, 0.1, 3.0]",
        "tokens": [
          "0.5",
          "0.1",
          "3.0"
        ],
        "value": 0.5
      },
      {
        "max": 1.0,
        "min": 0.0,
        "name": "sosP",
        "raw": "sosP[0.10, 0.0, 1.0]",
        "tokens": [
          "0.10",
          "0.0",
          "1.0"
        ],
        "value": 0.1
      },
      {
        "max": 1.0,
        "min": 0.0,
        "name": "sosF",
        "raw": "sosF[0.12, 0.0, 1.0]",
        "tokens": [
          "0.12",
          "0.0",
          "1.0"
        ],
        "value": 0.12
      },
      {
        "max": 3.5,
        "min": 1.4,
        "name": "alphaP",
        "raw": "alphaP[2.0, 1.4, 3.5]",
        "tokens": [
          "2.0",
          "1.4",
          "3.5"
        ],
        "value": 2.0
      },
      {
        "max": 1.5,
        "min": 0.0,
        "name": "nP",
        "raw": "nP[0.4, 0.0, 1.5]",
        "tokens": [
          "0.4",
          "0.0",
          "1.5"
        ],
        "value": 0.4
      },
      {
        "max": 3.5,
        "min": 1.4,
        "name": "alphaF",
        "raw": "alphaF[2.0, 1.4, 3.5]",
        "tokens": [
          "2.0",
          "1.4",
          "3.5"
        ],
        "value": 2.0
      },
      {
        "max": 1.5,
        "min": 0.0,
        "name": "nF",
        "raw": "nF[0.4, 0.0, 1.5]",
        "tokens": [
          "0.4",
          "0.0",
          "1.5"
        ],
        "value": 0.4
      },
      {
        "max": 0.0,
        "min": -1.0,
        "name": "alphaP_2",
        "raw": "alphaP_2[-0.012, -1, 0]",
        "tokens": [
          "-0.012",
          "-1",
          "0"
        ],
        "value": -0.012
      },
      {
        "max": 0.05,
        "min": -1.0,
        "name": "alphaF_2",
        "raw": "alphaF_2[-0.014, -1, 0.05]",
        "tokens": [
          "-0.014",
          "-1",
          "0.05"
        ],
        "value": -0.014
      }
    ],
    "effective_raw": [
      "meanP[-0.0, -5.0, 5.0]",
      "meanF[-0.0, -5.0, 5.0]",
      "sigmaP[0.5, 0.1, 2.0]",
      "sigmaF[0.5, 0.1, 2.0]",
      "sigmaP_2[0.5, 0.1, 2.0]",
      "sigmaF_2[0.5, 0.1, 3.0]",
      "sosP[0.10, 0.0, 1.0]",
      "sosF[0.12, 0.0, 1.0]",
      "alphaP[2.0, 1.4, 3.5]",
      "nP[0.4, 0.0, 1.5]",
      "alphaF[2.0, 1.4, 3.5]",
      "nF[0.4, 0.0, 1.5]",
      "alphaP_2[-0.012, -1, 0]",
      "alphaF_2[-0.014, -1, 0.05]"
    ],
    "functions": [
      "tailLeft[1]",
      "RooCBExGaussShapeTNP::sigResPass(x,meanP,expr('sqrt(sigmaP*sigmaP+sosP*sosP)',{sigmaP,sosP}),alphaP,nP, expr('sqrt(sigmaP_2*sigmaP_2+sosP*sosP)',{sigmaP_2,sosP}),tailLeft)",
      "RooCBExGaussShapeTNP::sigResFail(x,meanF,expr('sqrt(sigmaF*sigmaF+sosF*sosF)',{sigmaF,sosF}),alphaF,nF, expr('sqrt(sigmaF_2*sigmaF_2+sosF*sosF)',{sigmaF_2,sosF}),tailLeft)",
      "Exponential::bkgPass(x, alphaP_2)",
      "Exponential::bkgFail(x, alphaF_2)"
    ],
    "overrides": [],
    "requested_parsed": [
      {
        "max": 5.0,
        "min": -5.0,
        "name": "meanP",
        "raw": "meanP[-0.0, -5.0, 5.0]",
        "tokens": [
          "-0.0",
          "-5.0",
          "5.0"
        ],
        "value": -0.0
      },
      {
        "max": 5.0,
        "min": -5.0,
        "name": "meanF",
        "raw": "meanF[-0.0, -5.0, 5.0]",
        "tokens": [
          "-0.0",
          "-5.0",
          "5.0"
        ],
        "value": -0.0
      },
      {
        "max": 2.0,
        "min": 0.1,
        "name": "sigmaP",
        "raw": "sigmaP[0.5, 0.1, 2.0]",
        "tokens": [
          "0.5",
          "0.1",
          "2.0"
        ],
        "value": 0.5
      },
      {
        "max": 2.0,
        "min": 0.1,
        "name": "sigmaF",
        "raw": "sigmaF[0.5, 0.1, 2.0]",
        "tokens": [
          "0.5",
          "0.1",
          "2.0"
        ],
        "value": 0.5
      },
      {
        "max": 2.0,
        "min": 0.1,
        "name": "sigmaP_2",
        "raw": "sigmaP_2[0.5, 0.1, 2.0]",
        "tokens": [
          "0.5",
          "0.1",
          "2.0"
        ],
        "value": 0.5
      },
      {
        "max": 3.0,
        "min": 0.1,
        "name": "sigmaF_2",
        "raw": "sigmaF_2[0.5, 0.1, 3.0]",
        "tokens": [
          "0.5",
          "0.1",
          "3.0"
        ],
        "value": 0.5
      },
      {
        "max": 1.0,
        "min": 0.0,
        "name": "sosP",
        "raw": "sosP[0.10, 0.0, 1.0]",
        "tokens": [
          "0.10",
          "0.0",
          "1.0"
        ],
        "value": 0.1
      },
      {
        "max": 1.0,
        "min": 0.0,
        "name": "sosF",
        "raw": "sosF[0.12, 0.0, 1.0]",
        "tokens": [
          "0.12",
          "0.0",
          "1.0"
        ],
        "value": 0.12
      },
      {
        "max": 3.5,
        "min": 1.4,
        "name": "alphaP",
        "raw": "alphaP[2.0, 1.4, 3.5]",
        "tokens": [
          "2.0",
          "1.4",
          "3.5"
        ],
        "value": 2.0
      },
      {
        "max": 1.5,
        "min": 0.0,
        "name": "nP",
        "raw": "nP[0.4, 0.0, 1.5]",
        "tokens": [
          "0.4",
          "0.0",
          "1.5"
        ],
        "value": 0.4
      },
      {
        "max": 3.5,
        "min": 1.4,
        "name": "alphaF",
        "raw": "alphaF[2.0, 1.4, 3.5]",
        "tokens": [
          "2.0",
          "1.4",
          "3.5"
        ],
        "value": 2.0
      },
      {
        "max": 1.5,
        "min": 0.0,
        "name": "nF",
        "raw": "nF[0.4, 0.0, 1.5]",
        "tokens": [
          "0.4",
          "0.0",
          "1.5"
        ],
        "value": 0.4
      },
      {
        "max": 0.0,
        "min": -1.0,
        "name": "alphaP_2",
        "raw": "alphaP_2[-0.012, -1, 0]",
        "tokens": [
          "-0.012",
          "-1",
          "0"
        ],
        "value": -0.012
      },
      {
        "max": 0.05,
        "min": -1.0,
        "name": "alphaF_2",
        "raw": "alphaF_2[-0.014, -1, 0.05]",
        "tokens": [
          "-0.014",
          "-1",
          "0.05"
        ],
        "value": -0.014
      }
    ],
    "requested_raw": [
      "meanP[-0.0, -5.0, 5.0]",
      "meanF[-0.0, -5.0, 5.0]",
      "sigmaP[0.5, 0.1, 2.0]",
      "sigmaF[0.5, 0.1, 2.0]",
      "sigmaP_2[0.5, 0.1, 2.0]",
      "sigmaF_2[0.5, 0.1, 3.0]",
      "sosP[0.10, 0.0, 1.0]",
      "sosF[0.12, 0.0, 1.0]",
      "alphaP[2.0, 1.4, 3.5]",
      "nP[0.4, 0.0, 1.5]",
      "alphaF[2.0, 1.4, 3.5]",
      "nF[0.4, 0.0, 1.5]",
      "alphaP_2[-0.012, -1, 0]",
      "alphaF_2[-0.014, -1, 0.05]"
    ]
  }
}
