{
  "bin": {
    "cut": "ph_r9 > 0.96 && event_nPV >= 30.000000 && event_nPV < 35.000000 && ph_et >= 20.000000 && ph_et < 35.000000",
    "index": 12,
    "name": "bin12_event_nPV_30p00To35p00_ph_et_20p00To35p00",
    "title": "; 30.000 < event_nPV < 35.000; 20.000 < ph_et < 35.000",
    "vars": {
      "event_nPV": {
        "max": 35,
        "min": 30
      },
      "ph_et": {
        "max": 35,
        "min": 20
      }
    }
  },
  "created_at_utc": "2026-05-11T09:02:32.489014+00:00",
  "derived": {
    "efficiency": 0.9548073511063156,
    "efficiency_error": 0.0018188746876394398,
    "nSigF": {
      "error": 23.789489299353534,
      "isConstant": false,
      "max": 867.0,
      "min": 0.5,
      "name": "nSigF",
      "value": 577.8467643852788
    },
    "nSigP": {
      "error": 110.48249530175053,
      "isConstant": false,
      "max": 18313.5,
      "min": 0.5,
      "name": "nSigP",
      "value": 12208.453187729985
    }
  },
  "fit_metadata": {
    "bin_index": 12,
    "fail_hist_uses_pass_hist": false,
    "fit_range": {
      "max": 120.0,
      "min": 60.0
    },
    "truth_fail_template_uses_pass_hist": false,
    "truth_template_source": "/eos/home-p/pelai/HZa/root_TnP/hza_resolve_phcsev_hr9_bkg_2024_sf//TT_DY_MC_2024_hza_resolve_phcsev_hr9_bkg_2024_sf.root"
  },
  "fit_result": {
    "fail": {
      "covQual": 2,
      "edm": 0.0017530879948718101,
      "floatParsFinal": [
        {
          "error": 1.91337983036572,
          "isConstant": false,
          "max": 3.5,
          "min": 1.4,
          "name": "alphaF",
          "value": 1.4000559013579967
        },
        {
          "error": 0.651163192768495,
          "isConstant": false,
          "max": -0.029,
          "min": -1.0,
          "name": "alphaF_2",
          "value": -0.029000009150031092
        },
        {
          "error": 0.40034895394816994,
          "isConstant": false,
          "max": 4.3,
          "min": -5.0,
          "name": "meanF",
          "value": -0.5649533591099294
        },
        {
          "error": 0.746136411725717,
          "isConstant": false,
          "max": 867.0,
          "min": 0.5,
          "name": "nBkgF",
          "value": 0.5000005329206804
        },
        {
          "error": 0.19701781816321356,
          "isConstant": false,
          "max": 1.5,
          "min": 0.0,
          "name": "nF",
          "value": 0.08483447788395673
        },
        {
          "error": 23.789489299353534,
          "isConstant": false,
          "max": 867.0,
          "min": 0.5,
          "name": "nSigF",
          "value": 577.8467643852788
        },
        {
          "error": 1.4166570427599239,
          "isConstant": false,
          "max": 2.0,
          "min": 0.1,
          "name": "sigmaF",
          "value": 0.11335211982915692
        },
        {
          "error": 0.371819798414173,
          "isConstant": false,
          "max": 3.0,
          "min": 0.1,
          "name": "sigmaF_2",
          "value": 1.5389185280068942
        },
        {
          "error": 0.5766241585295915,
          "isConstant": false,
          "max": 1.0,
          "min": 0.0,
          "name": "sosF",
          "value": 0.0019523870965734713
        }
      ],
      "floatParsInit": [
        {
          "error": 0.0,
          "isConstant": false,
          "max": 3.5,
          "min": 1.4,
          "name": "alphaF",
          "value": 2.0
        },
        {
          "error": 0.0,
          "isConstant": false,
          "max": -0.029,
          "min": -1.0,
          "name": "alphaF_2",
          "value": -0.04
        },
        {
          "error": 0.0,
          "isConstant": false,
          "max": 4.3,
          "min": -5.0,
          "name": "meanF",
          "value": -1.0
        },
        {
          "error": 0.0,
          "isConstant": false,
          "max": 867.0,
          "min": 0.5,
          "name": "nBkgF",
          "value": 57.8
        },
        {
          "error": 0.0,
          "isConstant": false,
          "max": 1.5,
          "min": 0.0,
          "name": "nF",
          "value": 0.4
        },
        {
          "error": 0.0,
          "isConstant": false,
          "max": 867.0,
          "min": 0.5,
          "name": "nSigF",
          "value": 520.2
        },
        {
          "error": 0.0,
          "isConstant": false,
          "max": 2.0,
          "min": 0.1,
          "name": "sigmaF",
          "value": 0.5
        },
        {
          "error": 0.0,
          "isConstant": false,
          "max": 3.0,
          "min": 0.1,
          "name": "sigmaF_2",
          "value": 0.5
        },
        {
          "error": 0.0,
          "isConstant": false,
          "max": 1.0,
          "min": 0.0,
          "name": "sosF",
          "value": 0.12
        }
      ],
      "minNll": -1483.3377633286682,
      "numInvalidNLL": 0,
      "status": 0
    },
    "fail_quality": "ok",
    "pass": {
      "covQual": 3,
      "edm": 0.0005419613838822475,
      "floatParsFinal": [
        {
          "error": 1.6122622231458736,
          "isConstant": false,
          "max": 3.5,
          "min": 1.4,
          "name": "alphaP",
          "value": 1.4357881560588623
        },
        {
          "error": 0.7023455644518061,
          "isConstant": false,
          "max": 0.0,
          "min": -1.0,
          "name": "alphaP_2",
          "value": -6.716276472540361e-05
        },
        {
          "error": 0.06457202331777179,
          "isConstant": false,
          "max": 5.0,
          "min": -5.0,
          "name": "meanP",
          "value": 0.06121102990075844
        },
        {
          "error": 0.7889555931809596,
          "isConstant": false,
          "max": 18313.5,
          "min": 0.5,
          "name": "nBkgP",
          "value": 0.5000141550940111
        },
        {
          "error": 0.963114129258793,
          "isConstant": false,
          "max": 1.5,
          "min": 0.0,
          "name": "nP",
          "value": 1.4999976301204763
        },
        {
          "error": 110.48249530175053,
          "isConstant": false,
          "max": 18313.5,
          "min": 0.5,
          "name": "nSigP",
          "value": 12208.453187729985
        },
        {
          "error": 0.044161499178483804,
          "isConstant": false,
          "max": 2.0,
          "min": 0.1,
          "name": "sigmaP",
          "value": 0.10000004320324393
        },
        {
          "error": 0.05123204259425043,
          "isConstant": false,
          "max": 2.0,
          "min": 0.1,
          "name": "sigmaP_2",
          "value": 0.10000000789288979
        },
        {
          "error": 0.6946708375774178,
          "isConstant": false,
          "max": 1.0,
          "min": 0.0,
          "name": "sosP",
          "value": 7.436206313105043e-05
        }
      ],
      "floatParsInit": [
        {
          "error": 0.0,
          "isConstant": false,
          "max": 3.5,
          "min": 1.4,
          "name": "alphaP",
          "value": 2.0
        },
        {
          "error": 0.0,
          "isConstant": false,
          "max": 0.0,
          "min": -1.0,
          "name": "alphaP_2",
          "value": -0.012
        },
        {
          "error": 0.0,
          "isConstant": false,
          "max": 5.0,
          "min": -5.0,
          "name": "meanP",
          "value": -0.0
        },
        {
          "error": 0.0,
          "isConstant": false,
          "max": 18313.5,
          "min": 0.5,
          "name": "nBkgP",
          "value": 1220.9
        },
        {
          "error": 0.0,
          "isConstant": false,
          "max": 1.5,
          "min": 0.0,
          "name": "nP",
          "value": 0.4
        },
        {
          "error": 0.0,
          "isConstant": false,
          "max": 18313.5,
          "min": 0.5,
          "name": "nSigP",
          "value": 10988.1
        },
        {
          "error": 0.0,
          "isConstant": false,
          "max": 2.0,
          "min": 0.1,
          "name": "sigmaP",
          "value": 0.5
        },
        {
          "error": 0.0,
          "isConstant": false,
          "max": 2.0,
          "min": 0.1,
          "name": "sigmaP_2",
          "value": 0.5
        },
        {
          "error": 0.0,
          "isConstant": false,
          "max": 1.0,
          "min": 0.0,
          "name": "sosP",
          "value": 0.1
        }
      ],
      "minNll": -71208.28101002664,
      "numInvalidNLL": 0,
      "status": 0
    },
    "pass_quality": "ok",
    "root_read_error": null
  },
  "fit_type": "altSigBkgFit",
  "histograms": {
    "fail": {
      "entries": 578.0,
      "fit_window": {
        "bin1": 11,
        "bin2": 70,
        "max": 120.0,
        "min": 60.0
      },
      "integral_fit_window": 578.0,
      "integral_fit_window_error": 24.041630560342615,
      "integral_full": 578.0,
      "integral_full_error": 24.041630560342615,
      "maximum_bin_center": 91.5,
      "maximum_bin_content": 73.0,
      "mean": 90.360063123868,
      "rms": 3.9767428282040855
    },
    "pass": {
      "entries": 12209.0,
      "fit_window": {
        "bin1": 11,
        "bin2": 70,
        "max": 120.0,
        "min": 60.0
      },
      "integral_fit_window": 12209.0,
      "integral_fit_window_error": 110.4943437466371,
      "integral_full": 12209.0,
      "integral_full_error": 110.4943437466371,
      "maximum_bin_center": 91.5,
      "maximum_bin_content": 1960.0,
      "mean": 90.58611680108233,
      "rms": 3.359828378823368
    }
  },
  "sample": {
    "fitOutputBinRoot": "/eos/home-p/pelai/HZa/root_TnP/hza_resolve_phcsev_hr9_bkg_2024_sf//Data_2024_hza_resolve_phcsev_hr9_bkg_2024_sf.altSigBkgFit-bin12_event_nPV_30p00To35p00_ph_et_20p00To35p00.root",
    "fitOutputRoot": "/eos/home-p/pelai/HZa/root_TnP/hza_resolve_phcsev_hr9_bkg_2024_sf//Data_2024_hza_resolve_phcsev_hr9_bkg_2024_sf.altSigBkgFit.root",
    "histFile": "/eos/home-p/pelai/HZa/root_TnP/hza_resolve_phcsev_hr9_bkg_2024_sf//Data_2024_hza_resolve_phcsev_hr9_bkg_2024_sf.root",
    "isMC": false,
    "mcRefHistFile": "/eos/home-p/pelai/HZa/root_TnP/hza_resolve_phcsev_hr9_bkg_2024_sf//TT_DY_MC_2024_hza_resolve_phcsev_hr9_bkg_2024_sf.root",
    "mcTruth": false,
    "name": "Data_2024"
  },
  "workspace": {
    "effective_parsed": [
      {
        "max": 5.0,
        "min": -5.0,
        "name": "meanP",
        "raw": "meanP[-0.0, -5.0, 5.0]",
        "tokens": [
          "-0.0",
          "-5.0",
          "5.0"
        ],
        "value": -0.0
      },
      {
        "max": 2.0,
        "min": 0.1,
        "name": "sigmaP",
        "raw": "sigmaP[0.5, 0.1, 2.0]",
        "tokens": [
          "0.5",
          "0.1",
          "2.0"
        ],
        "value": 0.5
      },
      {
        "max": 2.0,
        "min": 0.1,
        "name": "sigmaP_2",
        "raw": "sigmaP_2[0.5, 0.1, 2.0]",
        "tokens": [
          "0.5",
          "0.1",
          "2.0"
        ],
        "value": 0.5
      },
      {
        "max": 1.0,
        "min": 0.0,
        "name": "sosP",
        "raw": "sosP[0.10, 0.0, 1.0]",
        "tokens": [
          "0.10",
          "0.0",
          "1.0"
        ],
        "value": 0.1
      },
      {
        "max": 4.3,
        "min": -5.0,
        "name": "meanF",
        "raw": "meanF[-1.0, -5.0, 4.3]",
        "tokens": [
          "-1.0",
          "-5.0",
          "4.3"
        ],
        "value": -1.0
      },
      {
        "max": 2.0,
        "min": 0.1,
        "name": "sigmaF",
        "raw": "sigmaF[0.5, 0.1, 2.0]",
        "tokens": [
          "0.5",
          "0.1",
          "2.0"
        ],
        "value": 0.5
      },
      {
        "max": 3.0,
        "min": 0.1,
        "name": "sigmaF_2",
        "raw": "sigmaF_2[0.5, 0.1, 3.0]",
        "tokens": [
          "0.5",
          "0.1",
          "3.0"
        ],
        "value": 0.5
      },
      {
        "max": 1.0,
        "min": 0.0,
        "name": "sosF",
        "raw": "sosF[0.12, 0.0, 1.0]",
        "tokens": [
          "0.12",
          "0.0",
          "1.0"
        ],
        "value": 0.12
      },
      {
        "max": 3.5,
        "min": 1.4,
        "name": "alphaP",
        "raw": "alphaP[2.0, 1.4, 3.5]",
        "tokens": [
          "2.0",
          "1.4",
          "3.5"
        ],
        "value": 2.0
      },
      {
        "max": 1.5,
        "min": 0.0,
        "name": "nP",
        "raw": "nP[0.4, 0.0, 1.5]",
        "tokens": [
          "0.4",
          "0.0",
          "1.5"
        ],
        "value": 0.4
      },
      {
        "max": 0.0,
        "min": -1.0,
        "name": "alphaP_2",
        "raw": "alphaP_2[-0.012, -1, 0]",
        "tokens": [
          "-0.012",
          "-1",
          "0"
        ],
        "value": -0.012
      },
      {
        "max": 3.5,
        "min": 1.4,
        "name": "alphaF",
        "raw": "alphaF[2.0, 1.4, 3.5]",
        "tokens": [
          "2.0",
          "1.4",
          "3.5"
        ],
        "value": 2.0
      },
      {
        "max": 1.5,
        "min": 0.0,
        "name": "nF",
        "raw": "nF[0.4, 0.0, 1.5]",
        "tokens": [
          "0.4",
          "0.0",
          "1.5"
        ],
        "value": 0.4
      },
      {
        "max": -0.029,
        "min": -1.0,
        "name": "alphaF_2",
        "raw": "alphaF_2[-0.04, -1, -0.029]",
        "tokens": [
          "-0.04",
          "-1",
          "-0.029"
        ],
        "value": -0.04
      }
    ],
    "effective_raw": [
      "meanP[-0.0, -5.0, 5.0]",
      "sigmaP[0.5, 0.1, 2.0]",
      "sigmaP_2[0.5, 0.1, 2.0]",
      "sosP[0.10, 0.0, 1.0]",
      "meanF[-1.0, -5.0, 4.3]",
      "sigmaF[0.5, 0.1, 2.0]",
      "sigmaF_2[0.5, 0.1, 3.0]",
      "sosF[0.12, 0.0, 1.0]",
      "alphaP[2.0, 1.4, 3.5]",
      "nP[0.4, 0.0, 1.5]",
      "alphaP_2[-0.012, -1, 0]",
      "alphaF[2.0, 1.4, 3.5]",
      "nF[0.4, 0.0, 1.5]",
      "alphaF_2[-0.04, -1, -0.029]"
    ],
    "functions": [
      "tailLeft[1]",
      "RooCBExGaussShapeTNP::sigResPass(x,meanP,expr('sqrt(sigmaP*sigmaP+sosP*sosP)',{sigmaP,sosP}),alphaP,nP, expr('sqrt(sigmaP_2*sigmaP_2+sosP*sosP)',{sigmaP_2,sosP}),tailLeft)",
      "RooCBExGaussShapeTNP::sigResFail(x,meanF,expr('sqrt(sigmaF*sigmaF+sosF*sosF)',{sigmaF,sosF}),alphaF,nF, expr('sqrt(sigmaF_2*sigmaF_2+sosF*sosF)',{sigmaF_2,sosF}),tailLeft)",
      "Exponential::bkgPass(x, alphaP_2)",
      "Exponential::bkgFail(x, alphaF_2)"
    ],
    "overrides": [],
    "requested_parsed": [
      {
        "max": 5.0,
        "min": -5.0,
        "name": "meanP",
        "raw": "meanP[-0.0, -5.0, 5.0]",
        "tokens": [
          "-0.0",
          "-5.0",
          "5.0"
        ],
        "value": -0.0
      },
      {
        "max": 2.0,
        "min": 0.1,
        "name": "sigmaP",
        "raw": "sigmaP[0.5, 0.1, 2.0]",
        "tokens": [
          "0.5",
          "0.1",
          "2.0"
        ],
        "value": 0.5
      },
      {
        "max": 2.0,
        "min": 0.1,
        "name": "sigmaP_2",
        "raw": "sigmaP_2[0.5, 0.1, 2.0]",
        "tokens": [
          "0.5",
          "0.1",
          "2.0"
        ],
        "value": 0.5
      },
      {
        "max": 1.0,
        "min": 0.0,
        "name": "sosP",
        "raw": "sosP[0.10, 0.0, 1.0]",
        "tokens": [
          "0.10",
          "0.0",
          "1.0"
        ],
        "value": 0.1
      },
      {
        "max": 4.3,
        "min": -5.0,
        "name": "meanF",
        "raw": "meanF[-1.0, -5.0, 4.3]",
        "tokens": [
          "-1.0",
          "-5.0",
          "4.3"
        ],
        "value": -1.0
      },
      {
        "max": 2.0,
        "min": 0.1,
        "name": "sigmaF",
        "raw": "sigmaF[0.5, 0.1, 2.0]",
        "tokens": [
          "0.5",
          "0.1",
          "2.0"
        ],
        "value": 0.5
      },
      {
        "max": 3.0,
        "min": 0.1,
        "name": "sigmaF_2",
        "raw": "sigmaF_2[0.5, 0.1, 3.0]",
        "tokens": [
          "0.5",
          "0.1",
          "3.0"
        ],
        "value": 0.5
      },
      {
        "max": 1.0,
        "min": 0.0,
        "name": "sosF",
        "raw": "sosF[0.12, 0.0, 1.0]",
        "tokens": [
          "0.12",
          "0.0",
          "1.0"
        ],
        "value": 0.12
      },
      {
        "max": 3.5,
        "min": 1.4,
        "name": "alphaP",
        "raw": "alphaP[2.0, 1.4, 3.5]",
        "tokens": [
          "2.0",
          "1.4",
          "3.5"
        ],
        "value": 2.0
      },
      {
        "max": 1.5,
        "min": 0.0,
        "name": "nP",
        "raw": "nP[0.4, 0.0, 1.5]",
        "tokens": [
          "0.4",
          "0.0",
          "1.5"
        ],
        "value": 0.4
      },
      {
        "max": 0.0,
        "min": -1.0,
        "name": "alphaP_2",
        "raw": "alphaP_2[-0.012, -1, 0]",
        "tokens": [
          "-0.012",
          "-1",
          "0"
        ],
        "value": -0.012
      },
      {
        "max": 3.5,
        "min": 1.4,
        "name": "alphaF",
        "raw": "alphaF[2.0, 1.4, 3.5]",
        "tokens": [
          "2.0",
          "1.4",
          "3.5"
        ],
        "value": 2.0
      },
      {
        "max": 1.5,
        "min": 0.0,
        "name": "nF",
        "raw": "nF[0.4, 0.0, 1.5]",
        "tokens": [
          "0.4",
          "0.0",
          "1.5"
        ],
        "value": 0.4
      },
      {
        "max": -0.029,
        "min": -1.0,
        "name": "alphaF_2",
        "raw": "alphaF_2[-0.04, -1, -0.029]",
        "tokens": [
          "-0.04",
          "-1",
          "-0.029"
        ],
        "value": -0.04
      }
    ],
    "requested_raw": [
      "meanP[-0.0, -5.0, 5.0]",
      "sigmaP[0.5, 0.1, 2.0]",
      "sigmaP_2[0.5, 0.1, 2.0]",
      "sosP[0.10, 0.0, 1.0]",
      "meanF[-1.0, -5.0, 4.3]",
      "sigmaF[0.5, 0.1, 2.0]",
      "sigmaF_2[0.5, 0.1, 3.0]",
      "sosF[0.12, 0.0, 1.0]",
      "alphaP[2.0, 1.4, 3.5]",
      "nP[0.4, 0.0, 1.5]",
      "alphaP_2[-0.012, -1, 0]",
      "alphaF[2.0, 1.4, 3.5]",
      "nF[0.4, 0.0, 1.5]",
      "alphaF_2[-0.04, -1, -0.029]"
    ]
  }
}
