{
  "bin": {
    "cut": "tag_Ele_pt > 35 && abs(tag_sc_eta) < 2.17 && ph_sc_eta >= 2.000000 && ph_sc_eta < 2.500000 && ph_et >= 10.000000 && ph_et < 20.000000 &&  !((ph_sc_eta > -1.566 && ph_sc_eta < 0) && (ph_sc_phi > -1.2 && ph_sc_phi < -0.8))  ",
    "index": 7,
    "name": "bin07_ph_sc_eta_2p00To2p50_ph_et_10p00To20p00",
    "title": "; 2.000 < ph_sc_eta < 2.500; 10.000 < ph_et < 20.000",
    "vars": {
      "ph_et": {
        "max": 20,
        "min": 10
      },
      "ph_sc_eta": {
        "max": 2.5,
        "min": 2.0
      }
    }
  },
  "created_at_utc": "2026-04-20T20:48:49.931819+00:00",
  "derived": {
    "efficiency": 0.8582712100795306,
    "efficiency_error": 0.010208592314038836,
    "nSigF": {
      "error": 194.99859333859717,
      "isConstant": false,
      "max": 103974.0,
      "min": 0.5,
      "name": "nSigF",
      "value": 2372.404317641032
    },
    "nSigP": {
      "error": 243.4736992121625,
      "isConstant": false,
      "max": 107337.0,
      "min": 0.5,
      "name": "nSigP",
      "value": 14366.638744621034
    }
  },
  "fit_metadata": {
    "bin_index": 7,
    "fail_hist_uses_pass_hist": false,
    "fit_range": {
      "max": 120.0,
      "min": 60.0
    },
    "truth_fail_template_uses_pass_hist": false,
    "truth_template_source": "/eos/home-p/pelai/HZa/root_TnP//hza_resolve_phid_lowpt_2023postBPix_sf//DY_MC_LO_2023postBPix_hza_resolve_phid_lowpt_2023postBPix_sf.root"
  },
  "fit_result": {
    "fail": {
      "covQual": 3,
      "edm": 0.08646532592913783,
      "floatParsFinal": [
        {
          "error": 0.0002952454367077806,
          "isConstant": false,
          "max": 5.0,
          "min": -5.0,
          "name": "alphaF",
          "value": -0.02542276480859673
        },
        {
          "error": 0.4258053329948235,
          "isConstant": false,
          "max": 5.0,
          "min": -5.0,
          "name": "meanF",
          "value": -2.431774628010218
        },
        {
          "error": 286.5211998208142,
          "isConstant": false,
          "max": 103974.0,
          "min": 0.5,
          "name": "nBkgF",
          "value": 46289.217720864865
        },
        {
          "error": 194.99859333859717,
          "isConstant": false,
          "max": 103974.0,
          "min": 0.5,
          "name": "nSigF",
          "value": 2372.404317641032
        },
        {
          "error": 0.30927517966646506,
          "isConstant": false,
          "max": 3.011173329853005,
          "min": 0.802979554627468,
          "name": "sigmaF",
          "value": 0.8754558787131348
        }
      ],
      "floatParsInit": [
        {
          "error": 0.0,
          "isConstant": false,
          "max": 5.0,
          "min": -5.0,
          "name": "alphaF",
          "value": 0.0
        },
        {
          "error": 0.0,
          "isConstant": false,
          "max": 5.0,
          "min": -5.0,
          "name": "meanF",
          "value": -0.0
        },
        {
          "error": 0.0,
          "isConstant": false,
          "max": 103974.0,
          "min": 0.5,
          "name": "nBkgF",
          "value": 6931.6
        },
        {
          "error": 0.0,
          "isConstant": false,
          "max": 103974.0,
          "min": 0.5,
          "name": "nSigF",
          "value": 62384.4
        },
        {
          "error": 0.0,
          "isConstant": false,
          "max": 3.011173329853005,
          "min": 0.802979554627468,
          "name": "sigmaF",
          "value": 1.0037244432843349
        }
      ],
      "minNll": -281596.37181455153,
      "numInvalidNLL": 0,
      "status": 3
    },
    "fail_quality": "check",
    "pass": {
      "covQual": 3,
      "edm": 2.0438461422466408e-05,
      "floatParsFinal": [
        {
          "error": 0.000319099836862069,
          "isConstant": false,
          "max": 5.0,
          "min": -5.0,
          "name": "alphaP",
          "value": -0.01747467745655662
        },
        {
          "error": 0.09467021862215486,
          "isConstant": false,
          "max": 5.0,
          "min": -5.0,
          "name": "meanP",
          "value": -2.136997702972145
        },
        {
          "error": 290.66590147573515,
          "isConstant": false,
          "max": 107337.0,
          "min": 0.5,
          "name": "nBkgP",
          "value": 39578.36682675099
        },
        {
          "error": 243.4736992121625,
          "isConstant": false,
          "max": 107337.0,
          "min": 0.5,
          "name": "nSigP",
          "value": 14366.638744621034
        },
        {
          "error": 0.25292544477569695,
          "isConstant": false,
          "max": 5.0,
          "min": 0.5,
          "name": "sigmaP",
          "value": 1.0037244432843349
        }
      ],
      "floatParsInit": [
        {
          "error": 0.0,
          "isConstant": false,
          "max": 5.0,
          "min": -5.0,
          "name": "alphaP",
          "value": 0.0
        },
        {
          "error": 0.0,
          "isConstant": false,
          "max": 5.0,
          "min": -5.0,
          "name": "meanP",
          "value": -0.0
        },
        {
          "error": 0.0,
          "isConstant": false,
          "max": 107337.0,
          "min": 0.5,
          "name": "nBkgP",
          "value": 7155.8
        },
        {
          "error": 0.0,
          "isConstant": false,
          "max": 107337.0,
          "min": 0.5,
          "name": "nSigP",
          "value": 64402.2
        },
        {
          "error": 0.0,
          "isConstant": false,
          "max": 5.0,
          "min": 0.5,
          "name": "sigmaP",
          "value": 0.9
        }
      ],
      "minNll": -317452.07762313867,
      "numInvalidNLL": 0,
      "status": 0
    },
    "pass_quality": "ok",
    "root_read_error": null
  },
  "fit_type": "altBkgFit",
  "histograms": {
    "fail": {
      "entries": 69316.0,
      "fit_window": {
        "bin1": 11,
        "bin2": 70,
        "max": 120.0,
        "min": 60.0
      },
      "integral_fit_window": 48655.0,
      "integral_fit_window_error": 220.5787841112558,
      "integral_full": 69316.0,
      "integral_full_error": 263.2793193549391,
      "maximum_bin_center": 52.5,
      "maximum_bin_content": 1792.0,
      "mean": 77.9406427931776,
      "rms": 21.093841988414624
    },
    "pass": {
      "entries": 71558.0,
      "fit_window": {
        "bin1": 11,
        "bin2": 70,
        "max": 120.0,
        "min": 60.0
      },
      "integral_fit_window": 53945.0,
      "integral_fit_window_error": 232.26062946612367,
      "integral_full": 71558.0,
      "integral_full_error": 267.5032710080383,
      "maximum_bin_center": 88.5,
      "maximum_bin_content": 1632.0,
      "mean": 81.29530375312808,
      "rms": 20.551805179103585
    }
  },
  "sample": {
    "fitOutputBinRoot": "/eos/home-p/pelai/HZa/root_TnP//hza_resolve_phid_lowpt_2023postBPix_sf//Data_2023postBPix_hza_resolve_phid_lowpt_2023postBPix_sf.altBkgFit-bin07_ph_sc_eta_2p00To2p50_ph_et_10p00To20p00.root",
    "fitOutputRoot": "/eos/home-p/pelai/HZa/root_TnP//hza_resolve_phid_lowpt_2023postBPix_sf//Data_2023postBPix_hza_resolve_phid_lowpt_2023postBPix_sf.altBkgFit.root",
    "histFile": "/eos/home-p/pelai/HZa/root_TnP//hza_resolve_phid_lowpt_2023postBPix_sf//Data_2023postBPix_hza_resolve_phid_lowpt_2023postBPix_sf.root",
    "isMC": false,
    "mcRefHistFile": "/eos/home-p/pelai/HZa/root_TnP//hza_resolve_phid_lowpt_2023postBPix_sf//DY_MC_LO_2023postBPix_hza_resolve_phid_lowpt_2023postBPix_sf.root",
    "mcTruth": false,
    "name": "Data_2023postBPix"
  },
  "workspace": {
    "effective_parsed": [
      {
        "max": 5.0,
        "min": -5.0,
        "name": "meanP",
        "raw": "meanP[-0.0,-5.0,5.0]",
        "tokens": [
          "-0.0",
          "-5.0",
          "5.0"
        ],
        "value": -0.0
      },
      {
        "max": 5.0,
        "min": 0.5,
        "name": "sigmaP",
        "raw": "sigmaP[0.9,0.5,5.0]",
        "tokens": [
          "0.9",
          "0.5",
          "5.0"
        ],
        "value": 0.9
      },
      {
        "max": 5.0,
        "min": -5.0,
        "name": "meanF",
        "raw": "meanF[-0.0,-5.0,5.0]",
        "tokens": [
          "-0.0",
          "-5.0",
          "5.0"
        ],
        "value": -0.0
      },
      {
        "max": 5.0,
        "min": 0.5,
        "name": "sigmaF",
        "raw": "sigmaF[0.9,0.5,5.0]",
        "tokens": [
          "0.9",
          "0.5",
          "5.0"
        ],
        "value": 0.9
      },
      {
        "max": 5.0,
        "min": -5.0,
        "name": "alphaP",
        "raw": "alphaP[0.,-5.,5.]",
        "tokens": [
          "0.",
          "-5.",
          "5."
        ],
        "value": 0.0
      },
      {
        "max": 5.0,
        "min": -5.0,
        "name": "alphaF",
        "raw": "alphaF[0.,-5.,5.]",
        "tokens": [
          "0.",
          "-5.",
          "5."
        ],
        "value": 0.0
      }
    ],
    "effective_raw": [
      "meanP[-0.0,-5.0,5.0]",
      "sigmaP[0.9,0.5,5.0]",
      "meanF[-0.0,-5.0,5.0]",
      "sigmaF[0.9,0.5,5.0]",
      "alphaP[0.,-5.,5.]",
      "alphaF[0.,-5.,5.]"
    ],
    "functions": [
      "Gaussian::sigResPass(x,meanP,sigmaP)",
      "Gaussian::sigResFail(x,meanF,sigmaF)",
      "Exponential::bkgPass(x, alphaP)",
      "Exponential::bkgFail(x, alphaF)"
    ],
    "overrides": [],
    "requested_parsed": [
      {
        "max": 5.0,
        "min": -5.0,
        "name": "meanP",
        "raw": "meanP[-0.0,-5.0,5.0]",
        "tokens": [
          "-0.0",
          "-5.0",
          "5.0"
        ],
        "value": -0.0
      },
      {
        "max": 5.0,
        "min": 0.5,
        "name": "sigmaP",
        "raw": "sigmaP[0.9,0.5,5.0]",
        "tokens": [
          "0.9",
          "0.5",
          "5.0"
        ],
        "value": 0.9
      },
      {
        "max": 5.0,
        "min": -5.0,
        "name": "meanF",
        "raw": "meanF[-0.0,-5.0,5.0]",
        "tokens": [
          "-0.0",
          "-5.0",
          "5.0"
        ],
        "value": -0.0
      },
      {
        "max": 5.0,
        "min": 0.5,
        "name": "sigmaF",
        "raw": "sigmaF[0.9,0.5,5.0]",
        "tokens": [
          "0.9",
          "0.5",
          "5.0"
        ],
        "value": 0.9
      },
      {
        "max": 5.0,
        "min": -5.0,
        "name": "alphaP",
        "raw": "alphaP[0.,-5.,5.]",
        "tokens": [
          "0.",
          "-5.",
          "5."
        ],
        "value": 0.0
      },
      {
        "max": 5.0,
        "min": -5.0,
        "name": "alphaF",
        "raw": "alphaF[0.,-5.,5.]",
        "tokens": [
          "0.",
          "-5.",
          "5."
        ],
        "value": 0.0
      }
    ],
    "requested_raw": [
      "meanP[-0.0,-5.0,5.0]",
      "sigmaP[0.9,0.5,5.0]",
      "meanF[-0.0,-5.0,5.0]",
      "sigmaF[0.9,0.5,5.0]",
      "alphaP[0.,-5.,5.]",
      "alphaF[0.,-5.,5.]"
    ]
  }
}
