{
  "bin": {
    "cut": "tag_Ele_pt > 40 && abs(tag_sc_eta) < 2.17 && (tag_Ele_q + el_q) == 0 &&(((el_pt > 7) &&(abs(el_sc_eta) < 2.5) &&(abs(el_dz) < 1.0) &&(abs(el_dxy) < 0.5) &&(el_sc_et > 10) && (    (abs(el_sc_eta) < 0.8   && el_hzzMVA > 0.3527) || (abs(el_sc_eta) >= 0.8  && abs(el_sc_eta) < 1.479 && el_hzzMVA > 0.2601) || (abs(el_sc_eta) >= 1.479 && el_hzzMVA > -0.4954) )&& ( ((passHltEle23Ele12CaloIdLTrackIdLIsoVLLeg2 == 1 && el_hltE23E12leg2_dR < 0.3 && pair_lead_el_sc_et > 15 ) && (passHltEle23Ele12CaloIdLTrackIdLIsoVLLeg1L1match == 1) && el_hltE23E12leg1_dR < 0.3 && pair_lead_el_sc_et > 25 ) || (passHltEle30WPTightGsf == 1 && el_hltE30single_dR < 0.3 && pair_lead_el_sc_et > 35))) || ((el_pt > 7) &&(abs(el_sc_eta) < 2.5) &&(abs(el_dz) < 1.0) &&(abs(el_dxy) < 0.5) &&(el_sc_et < 10) && (    (abs(el_sc_eta) < 0.8   && el_hzzMVA > 0.9267) || (abs(el_sc_eta) >= 0.8  && abs(el_sc_eta) < 1.479 && el_hzzMVA > 0.9138) || (abs(el_sc_eta) >= 1.479 && el_hzzMVA > 0.9683) )&& ( ((passHltEle23Ele12CaloIdLTrackIdLIsoVLLeg2 == 1 && el_hltE23E12leg2_dR < 0.3 && pair_lead_el_sc_et > 15 ) && (passHltEle23Ele12CaloIdLTrackIdLIsoVLLeg1L1match == 1) && el_hltE23E12leg1_dR < 0.3 && pair_lead_el_sc_et > 25 ) || (passHltEle30WPTightGsf == 1 && el_hltE30single_dR < 0.3 && pair_lead_el_sc_et > 35)))) && el_sc_eta >= 0.000000 && el_sc_eta < 0.800000 && el_et >= 35.000000 && el_et < 50.000000",
    "index": 28,
    "name": "bin28_el_sc_eta_0p00To0p80_el_et_35p00To50p00",
    "title": "; 0.000 < el_sc_eta < 0.800; 35.000 < el_et < 50.000",
    "vars": {
      "el_et": {
        "max": 50,
        "min": 35
      },
      "el_sc_eta": {
        "max": 0.8,
        "min": 0.0
      }
    }
  },
  "created_at_utc": "2026-07-10T20:10:28.987952+00:00",
  "derived": {
    "efficiency": 0.9836225850623304,
    "efficiency_error": 5.54625712843404e-05,
    "nSigF": {
      "error": 294.0966542011447,
      "isConstant": false,
      "max": 129987.0,
      "min": 0.5,
      "name": "nSigF",
      "value": 86153.41231729428
    },
    "nSigP": {
      "error": 2318.223734510131,
      "isConstant": false,
      "max": 7822824.0,
      "min": 0.5,
      "name": "nSigP",
      "value": 5174347.872237296
    }
  },
  "fit_metadata": {
    "bin_index": 28,
    "fail_hist_uses_pass_hist": false,
    "fit_range": {
      "max": 120.0,
      "min": 60.0
    },
    "truth_fail_template_uses_pass_hist": false,
    "truth_template_source": "/eos/cms/store/group/phys_susy/NPS-25-014/root_TnP_local//hza_elminiIso0p15_nongap_2024_sf//DY_MC_LO_2024_hza_elminiIso0p15_nongap_2024_sf.root"
  },
  "fit_result": {
    "fail": {
      "covQual": 3,
      "edm": 0.0006211763479305174,
      "floatParsFinal": [
        {
          "error": 0.07062902064060506,
          "isConstant": false,
          "max": 5.0,
          "min": -5.0,
          "name": "alphaF",
          "value": -0.18026144350190698
        },
        {
          "error": 0.011688158717483077,
          "isConstant": false,
          "max": 5.0,
          "min": -5.0,
          "name": "meanF",
          "value": 0.08957810970865054
        },
        {
          "error": 20.265587962693893,
          "isConstant": false,
          "max": 129987.0,
          "min": 0.5,
          "name": "nBkgF",
          "value": 72.53265636501835
        },
        {
          "error": 294.0966542011447,
          "isConstant": false,
          "max": 129987.0,
          "min": 0.5,
          "name": "nSigF",
          "value": 86153.41231729428
        },
        {
          "error": 0.027605895873224928,
          "isConstant": false,
          "max": 5.0,
          "min": 0.5,
          "name": "sigmaF",
          "value": 0.8093353806250954
        }
      ],
      "floatParsInit": [
        {
          "error": 0.0,
          "isConstant": false,
          "max": 5.0,
          "min": -5.0,
          "name": "alphaF",
          "value": 0.0
        },
        {
          "error": 0.0,
          "isConstant": false,
          "max": 5.0,
          "min": -5.0,
          "name": "meanF",
          "value": -0.0
        },
        {
          "error": 0.0,
          "isConstant": false,
          "max": 129987.0,
          "min": 0.5,
          "name": "nBkgF",
          "value": 8665.8
        },
        {
          "error": 0.0,
          "isConstant": false,
          "max": 129987.0,
          "min": 0.5,
          "name": "nSigF",
          "value": 77992.2
        },
        {
          "error": 0.0,
          "isConstant": false,
          "max": 5.0,
          "min": 0.5,
          "name": "sigmaF",
          "value": 0.9
        }
      ],
      "minNll": -642499.3315002826,
      "numInvalidNLL": 0,
      "status": 0
    },
    "fail_quality": "ok",
    "pass": {
      "covQual": 3,
      "edm": 0.005308659186904005,
      "floatParsFinal": [
        {
          "error": 0.0007729293021254691,
          "isConstant": false,
          "max": 5.0,
          "min": -5.0,
          "name": "alphaP",
          "value": 0.010290656277430976
        },
        {
          "error": 0.001298873827447089,
          "isConstant": false,
          "max": 5.0,
          "min": -5.0,
          "name": "meanP",
          "value": -0.03432895966393268
        },
        {
          "error": 472.23888582833206,
          "isConstant": false,
          "max": 7822824.0,
          "min": 0.5,
          "name": "nBkgP",
          "value": 23441.933620147065
        },
        {
          "error": 2318.223734510131,
          "isConstant": false,
          "max": 7822824.0,
          "min": 0.5,
          "name": "nSigP",
          "value": 5174347.872237296
        },
        {
          "error": 0.003131852642877797,
          "isConstant": false,
          "max": 5.0,
          "min": 0.5,
          "name": "sigmaP",
          "value": 0.8304441722872874
        }
      ],
      "floatParsInit": [
        {
          "error": 0.0,
          "isConstant": false,
          "max": 5.0,
          "min": -5.0,
          "name": "alphaP",
          "value": 0.0
        },
        {
          "error": 0.0,
          "isConstant": false,
          "max": 5.0,
          "min": -5.0,
          "name": "meanP",
          "value": -0.0
        },
        {
          "error": 0.0,
          "isConstant": false,
          "max": 7822824.0,
          "min": 0.5,
          "name": "nBkgP",
          "value": 521521.6
        },
        {
          "error": 0.0,
          "isConstant": false,
          "max": 7822824.0,
          "min": 0.5,
          "name": "nSigP",
          "value": 4693694.4
        },
        {
          "error": 0.0,
          "isConstant": false,
          "max": 5.0,
          "min": 0.5,
          "name": "sigmaP",
          "value": 0.9
        }
      ],
      "minNll": -61103692.97771364,
      "numInvalidNLL": 0,
      "status": 0
    },
    "pass_quality": "ok",
    "root_read_error": null
  },
  "fit_type": "altBkgFit",
  "histograms": {
    "fail": {
      "entries": 86658.0,
      "fit_window": {
        "bin1": 11,
        "bin2": 70,
        "max": 120.0,
        "min": 60.0
      },
      "integral_fit_window": 86224.0,
      "integral_fit_window_error": 293.63923443572725,
      "integral_full": 86658.0,
      "integral_full_error": 294.3773089081426,
      "maximum_bin_center": 90.5,
      "maximum_bin_content": 11427.0,
      "mean": 90.59171075831267,
      "rms": 5.7219076862265625
    },
    "pass": {
      "entries": 5215216.0,
      "fit_window": {
        "bin1": 11,
        "bin2": 70,
        "max": 120.0,
        "min": 60.0
      },
      "integral_fit_window": 5197790.0,
      "integral_fit_window_error": 2279.8662241456186,
      "integral_full": 5215216.0,
      "integral_full_error": 2283.684741815297,
      "maximum_bin_center": 90.5,
      "maximum_bin_content": 781237.0,
      "mean": 91.21161188731507,
      "rms": 4.763848085683628
    }
  },
  "sample": {
    "fitOutputBinRoot": "/eos/cms/store/group/phys_susy/NPS-25-014/root_TnP_local//hza_elminiIso0p15_nongap_2024_sf//Data_2024_hza_elminiIso0p15_nongap_2024_sf.altBkgFit-bin28_el_sc_eta_0p00To0p80_el_et_35p00To50p00.root",
    "fitOutputRoot": "/eos/cms/store/group/phys_susy/NPS-25-014/root_TnP_local//hza_elminiIso0p15_nongap_2024_sf//Data_2024_hza_elminiIso0p15_nongap_2024_sf.altBkgFit.root",
    "histFile": "/eos/cms/store/group/phys_susy/NPS-25-014/root_TnP_local//hza_elminiIso0p15_nongap_2024_sf//Data_2024_hza_elminiIso0p15_nongap_2024_sf.root",
    "isMC": false,
    "mcRefHistFile": "/eos/cms/store/group/phys_susy/NPS-25-014/root_TnP_local//hza_elminiIso0p15_nongap_2024_sf//DY_MC_LO_2024_hza_elminiIso0p15_nongap_2024_sf.root",
    "mcTruth": false,
    "name": "Data_2024"
  },
  "workspace": {
    "effective_parsed": [
      {
        "max": 5.0,
        "min": -5.0,
        "name": "meanP",
        "raw": "meanP[-0.0,-5.0,5.0]",
        "tokens": [
          "-0.0",
          "-5.0",
          "5.0"
        ],
        "value": -0.0
      },
      {
        "max": 5.0,
        "min": 0.5,
        "name": "sigmaP",
        "raw": "sigmaP[0.9,0.5,5.0]",
        "tokens": [
          "0.9",
          "0.5",
          "5.0"
        ],
        "value": 0.9
      },
      {
        "max": 5.0,
        "min": -5.0,
        "name": "meanF",
        "raw": "meanF[-0.0,-5.0,5.0]",
        "tokens": [
          "-0.0",
          "-5.0",
          "5.0"
        ],
        "value": -0.0
      },
      {
        "max": 5.0,
        "min": 0.5,
        "name": "sigmaF",
        "raw": "sigmaF[0.9,0.5,5.0]",
        "tokens": [
          "0.9",
          "0.5",
          "5.0"
        ],
        "value": 0.9
      },
      {
        "max": 5.0,
        "min": -5.0,
        "name": "alphaP",
        "raw": "alphaP[0.,-5.,5.]",
        "tokens": [
          "0.",
          "-5.",
          "5."
        ],
        "value": 0.0
      },
      {
        "max": 5.0,
        "min": -5.0,
        "name": "alphaF",
        "raw": "alphaF[0.,-5.,5.]",
        "tokens": [
          "0.",
          "-5.",
          "5."
        ],
        "value": 0.0
      }
    ],
    "effective_raw": [
      "meanP[-0.0,-5.0,5.0]",
      "sigmaP[0.9,0.5,5.0]",
      "meanF[-0.0,-5.0,5.0]",
      "sigmaF[0.9,0.5,5.0]",
      "alphaP[0.,-5.,5.]",
      "alphaF[0.,-5.,5.]"
    ],
    "functions": [
      "Gaussian::sigResPass(x,meanP,sigmaP)",
      "Gaussian::sigResFail(x,meanF,sigmaF)",
      "Exponential::bkgPass(x, alphaP)",
      "Exponential::bkgFail(x, alphaF)"
    ],
    "overrides": [],
    "requested_parsed": [
      {
        "max": 5.0,
        "min": -5.0,
        "name": "meanP",
        "raw": "meanP[-0.0,-5.0,5.0]",
        "tokens": [
          "-0.0",
          "-5.0",
          "5.0"
        ],
        "value": -0.0
      },
      {
        "max": 5.0,
        "min": 0.5,
        "name": "sigmaP",
        "raw": "sigmaP[0.9,0.5,5.0]",
        "tokens": [
          "0.9",
          "0.5",
          "5.0"
        ],
        "value": 0.9
      },
      {
        "max": 5.0,
        "min": -5.0,
        "name": "meanF",
        "raw": "meanF[-0.0,-5.0,5.0]",
        "tokens": [
          "-0.0",
          "-5.0",
          "5.0"
        ],
        "value": -0.0
      },
      {
        "max": 5.0,
        "min": 0.5,
        "name": "sigmaF",
        "raw": "sigmaF[0.9,0.5,5.0]",
        "tokens": [
          "0.9",
          "0.5",
          "5.0"
        ],
        "value": 0.9
      },
      {
        "max": 5.0,
        "min": -5.0,
        "name": "alphaP",
        "raw": "alphaP[0.,-5.,5.]",
        "tokens": [
          "0.",
          "-5.",
          "5."
        ],
        "value": 0.0
      },
      {
        "max": 5.0,
        "min": -5.0,
        "name": "alphaF",
        "raw": "alphaF[0.,-5.,5.]",
        "tokens": [
          "0.",
          "-5.",
          "5."
        ],
        "value": 0.0
      }
    ],
    "requested_raw": [
      "meanP[-0.0,-5.0,5.0]",
      "sigmaP[0.9,0.5,5.0]",
      "meanF[-0.0,-5.0,5.0]",
      "sigmaF[0.9,0.5,5.0]",
      "alphaP[0.,-5.,5.]",
      "alphaF[0.,-5.,5.]"
    ]
  }
}
